{"items": [{"t": "a", "k": "ethelbeatriceabrahams", "n": "Abrahams, Ethel Beatrice", "c": 1}, {"t": "a", "k": "charlesjabbey", "n": "Abbey, Charles J.", "c": 1}, {"t": "a", "k": "bellekabbott", "n": "Abbott, Belle K.", "c": 1}, {"t": "a", "k": "charlescabbott", "n": "Abbott, Charles C.", "c": 2}, {"t": "a", "k": "cookrobertabbot", "n": "Abbot, cook Robert", "c": 1}, {"t": "a", "k": "arpadabonyi", "n": "Abonyi, Árpád", "c": 1}, {"t": "a", "k": "joaberg", "n": "Åberg, J. O.", "c": 16}, {"t": "a", "k": "janeabbott", "n": "Abbott, Jane", "c": 6}, {"t": "a", "k": "johnabercrombie", "n": "Abercrombie, John", "c": 1}, {"t": "a", "k": "lymanabbott", "n": "Abbott, Lyman", "c": 2}, {"t": "a", "k": "francisellingwoodabbot", "n": "Abbot, Francis Ellingwood", "c": 1}, {"t": "a", "k": "francisabell", "n": "Abell, Francis", "c": 1}, {"t": "a", "k": "edmondabout", "n": "About, Edmond", "c": 20}, {"t": "a", "k": "edwardabram", "n": "Abram, Edward", "c": 1}, {"t": "a", "k": "lemuelabijahabbott", "n": "Abbott, Lemuel Abijah", "c": 1}, {"t": "a", "k": "prussiaarmeegrossergeneralstabkriegsgeschichtlicheabteilungii", "n": "Abteilung II, Prussia . Armee. Grosser Generalstab. Kriegsgeschichtliche", "c": 1}, {"t": "a", "k": "sirwilliamdewiveleslieabney", "n": "Abney, Sir William de Wiveleslie", "c": 2}, {"t": "a", "k": "henryabbott", "n": "Abbott, Henry", "c": 6}, {"t": "a", "k": "henryabbey", "n": "Abbey, Henry", "c": 1}, {"t": "a", "k": "laabbott", "n": "Abbott, L. A.", "c": 1}, {"t": "a", "k": "annieheloiseabel", "n": "Abel, Annie Heloise", "c": 2}, {"t": "a", "k": "israelabrahams", "n": "Abrahams, Israel", "c": 4}, {"t": "a", "k": "tulisabrojal", "n": "Abrojal, Tulis", "c": 1}, {"t": "a", "k": "keeneabbott", "n": "Abbott, Keene", "c": 1}, {"t": "a", "k": "ashleyperryabraham", "n": "Abraham, Ashley Perry", "c": 1}, {"t": "a", "k": "robertabernathy", "n": "Abernathy, Robert", "c": 14}, {"t": "a", "k": "franklinabel", "n": "Abel, Franklin", "c": 1}, {"t": "a", "k": "willisjabbot", "n": "Abbot, Willis J.", "c": 5}, {"t": "a", "k": "johnloraineabbott", "n": "Abbott, John Loraine", "c": 1}, {"t": "a", "k": "peterabelard", "n": "Abelard, Peter", "c": 4}, {"t": "a", "k": "johnscabbott", "n": "Abbott, John S. C.", "c": 30}, {"t": "a", "k": "giuseppecesareabba", "n": "Abba, Giuseppe Cesare", "c": 1}, {"t": "a", "k": "jacobabbott", "n": "Abbott, Jacob", "c": 57}, {"t": "a", "k": "ernstabbe", "n": "Abbe, Ernst", "c": 1}, {"t": "a", "k": "wilburcortezabbott", "n": "Abbott, Wilbur Cortez", "c": 1}, {"t": "a", "k": "frankfrostabbott", "n": "Abbott, Frank Frost", "c": 2}, {"t": "a", "k": "stabert", "n": "Abert, S. T.", "c": 1}, {"t": "a", "k": "achmedabdullah", "n": "Abdullah, Achmed", "c": 1}, {"t": "a", "k": "lascellesabercrombie", "n": "Abercrombie, Lascelles", "c": 2}, {"t": "a", "k": "gfabbott", "n": "Abbott, G. F.", "c": 3}, {"t": "a", "k": "barbaraabel", "n": "Abel, Barbara", "c": 1}, {"t": "a", "k": "edwinabbottabbott", "n": "Abbott, Edwin Abbott", "c": 8}, {"t": "a", "k": "duchessedlaurejunotabrantes", "n": "Abrantès, duchesse d' Laure Junot", "c": 6}, {"t": "a", "k": "alexstclairabrams", "n": "Abrams, Alex. St. Clair", "c": 1}, {"t": "a", "k": "swamiabhedananda", "n": "Abhedananda, Swami", "c": 1}, {"t": "a", "k": "georgeaberighmackay", "n": "Aberigh-Mackay, George", "c": 1}, {"t": "a", "k": "ernesthamlinabbott", "n": "Abbott, Ernest Hamlin", "c": 1}, {"t": "a", "k": "eleanorhallowellabbott", "n": "Abbott, Eleanor Hallowell", "c": 10}, {"id": "62271", "title": "A Boy's Experience in the Civil War, 1860-1865", "a": "Hughes, Thomas", "k": "thomashughes", "cover": "/books/content/62271/OEBPS/2499344739692702899_cover.jpg"}, {"id": "10127", "title": "Abducted to Oz", "a": "Evans, Robert J.", "k": "robertjevans", "cover": "/books/content/10127/OEBPS/5520401511868121211_10127-cover.png"}, {"id": "50879", "title": "A Baptist Abroad: Travels and Adventures of Europe and all Bible Lands", "a": "Whittle, Walter Andrew", "k": "walterandrewwhittle", "cover": "/books/content/50879/OEBPS/392693545887931426_cover.jpg"}, {"id": "62480", "title": "Above the French Lines / Letters of Stuart Walcott, American Aviator: July 4, 1917, to December 8, 1917", "a": "Walcott, Stuart", "k": "stuartwalcott", "cover": "/books/content/62480/OEBPS/6819674225328483838_cover.jpg"}, {"id": "44322", "title": "A Bird of Passage, and Other Stories", "a": "Harraden, Beatrice", "k": "beatriceharraden", "cover": "/books/content/44322/OEBPS/6477756853923219474_img-cover.jpg"}, {"id": "12334", "title": "A Bicycle of Cathay", "a": "Stockton, Frank R.", "k": "frankrstockton", "cover": "/books/content/12334/OEBPS/1989496329695004952_12334-cover.png"}, {"id": "7361", "title": "A Brief History of Panics and Their Periodical Occurrence in the United States", "a": "Juglar, Clément", "k": "clementjuglar", "cover": "/books/content/7361/OEBPS/2732425802687332416_7361-cover.png"}, {"id": "61199", "title": "A Bad Town for Spacemen", "a": "Scott, Robert", "k": "robertscott", "cover": "/books/content/61199/OEBPS/7168917428711411080_cover.jpg"}, {"id": "12800", "title": "Abraham Lincoln, Volume I", "a": "Morse, Jr. John T.", "k": "jrjohntmorse", "cover": "/books/content/12800/OEBPS/2438733162914898736_12800-cover.png"}, {"id": "12801", "title": "Abraham Lincoln, Volume II", "a": "Morse, Jr. John T.", "k": "jrjohntmorse", "cover": "/books/content/12801/OEBPS/1605620617325454973_12801-cover.png"}, {"id": "53190", "title": "Absurd Ditties", "a": "Farrow, G. E.", "k": "gefarrow", "cover": "/books/content/53190/OEBPS/2634218585178233573_cover.jpg"}, {"id": "26599", "title": "A Black Adonis", "a": "Porter, Linn Boyd", "k": "linnboydporter", "cover": "/books/content/26599/OEBPS/4328419331932462176_fcover.jpg"}, {"id": "64204", "title": "Abnormitäten", "a": "Saltarino, Signor", "k": "signorsaltarino", "cover": "/books/content/64204/OEBPS/2160071646662770025_cover.jpg"}, {"id": "1331", "title": "ABC's of Science", "a": "Oliver, Charles A.", "k": "charlesaoliver", "cover": "/books/content/1331/OEBPS/5971494174478934257_1331-cover.png"}, {"id": "67712", "title": "A Bélteky ház: Tanregény (1. kötet)", "a": "Fáy, András", "k": "andrasfay", "cover": "/books/content/67712/OEBPS/1158556277524329361_cover.jpg"}, {"id": "67713", "title": "A Bélteky ház: Tanregény (2. kötet)", "a": "Fáy, András", "k": "andrasfay", "cover": "/books/content/67713/OEBPS/5636488338219082634_cover.jpg"}, {"id": "21665", "title": "A Brief History of the English Language and Literature, Vol. 2", "a": "Meiklejohn, J. M. D.", "k": "jmdmeiklejohn", "cover": "/books/content/21665/OEBPS/6627962967859417670_21665-cover.png"}, {"id": "50819", "title": "A Bad Day for Sales", "a": "Leiber, Fritz", "k": "fritzleiber", "cover": "/books/content/50819/OEBPS/6555526300193422553_cover.jpg"}, {"id": "23699", "title": "Abijah's Bubble", "a": "Smith, Francis Hopkinson", "k": "francishopkinsonsmith", "cover": "/books/content/23699/OEBPS/5956686520237392739_23699-cover.png"}, {"id": "70139", "title": "A bitter reckoning;", "a": "Collins, Mrs. E. Burke", "k": "mrseburkecollins", "cover": "/books/content/70139/OEBPS/2516568910275427592_cover.jpg"}, {"id": "9188", "title": "Aboriginal American Authors", "a": "Brinton, Daniel G.", "k": "danielgbrinton", "cover": "/books/content/9188/OEBPS/8205511125385935251_9188-cover.png"}, {"id": "45955", "title": "A-B-C of Electricity", "a": "Meadowcroft, Wm. H.", "k": "wmhmeadowcroft", "cover": "/books/content/45955/OEBPS/5416288934176973217_cover.jpg"}, {"id": "32365", "title": "A Boy Knight", "a": "Scott, Martin J.", "k": "martinjscott", "cover": "/books/content/32365/OEBPS/6260335208709197217_32365-cover.png"}, {"id": "19034", "title": "AbrakadabraL Storia dell'avvenire", "a": "Ghislanzoni, Antonio", "k": "antonioghislanzoni", "cover": "/books/content/19034/OEBPS/1627224968819219095_19034-cover.png"}, {"id": "63667", "title": "A Boy's Adventures Round the World", "a": "Higginson, John Andrew", "k": "johnandrewhigginson", "cover": "/books/content/63667/OEBPS/3501216694007634203_img-cover.jpg"}, {"id": "74971", "title": "A-B-C of motion pictures", "a": "Welsh, Robert E.", "k": "robertewelsh", "cover": "/books/content/74971/OEBPS/7670650858155205014_cover.jpg"}, {"id": "49861", "title": "A Bachelor's Comedy", "a": "Buckrose, J. E.", "k": "jebuckrose", "cover": "/books/content/49861/OEBPS/3959063390564872632_cover.jpg"}, {"id": "38582", "title": "Abraham Lincoln's Cardinal Traits; / A Study in Ethics, with an Epilogue Addressed to Theologians", "a": "Beardslee, Clark S.", "k": "clarksbeardslee", "cover": "/books/content/38582/OEBPS/9212729197385728529_38582-cover.png"}, {"id": "54380", "title": "A Battle of the Books, recorded by an unknown writer for the use of authors and publishers / To the first for doctrine, to the second for reproof, to both for correction and for instruction in righteousness", "a": "Hamilton, Gail", "k": "gailhamilton", "cover": "/books/content/54380/OEBPS/4445192482401031124_i_title.jpg"}, {"id": "49439", "title": "A Book of Porcelain: Fine examples in the Victoria & Albert Museum", "a": "Rackham, Bernard", "k": "bernardrackham", "cover": "/books/content/49439/OEBPS/1003803958747062725_cover.jpg"}, {"id": "72495", "title": "A brief course in the teaching process", "a": "Strayer, George D.", "k": "georgedstrayer", "cover": "/books/content/72495/OEBPS/8879205266339408358_cover.jpg"}, {"id": "54725", "title": "A Butterfly Chase", "a": "Stahl, P.-J.", "k": "pjstahl", "cover": "/books/content/54725/OEBPS/8493670709675211162_cover.jpg"}, {"id": "47150", "title": "A Book of Burlesque: Sketches of English Stage Travestie and Parody", "a": "Adams, William Davenport", "k": "williamdavenportadams", "cover": "/books/content/47150/OEBPS/8227074565985342126_i_cover.jpg"}, {"id": "19572", "title": "Absolute Surrender and Other Addresses", "a": "Murray, Andrew", "k": "andrewmurray", "cover": ""}, {"id": "60091", "title": "A Brief History of the Worshipful Company of Ironmongers, London A.D. 1351-1889 / With an Appendix Containing Some Account of the Blacksmiths' Company", "a": "Noble, T. C.", "k": "tcnoble", "cover": "/books/content/60091/OEBPS/1123736823142537195_cover.jpg"}, {"id": "67307", "title": "Aboe Bakar: Indische Roman", "a": "Daum, P. A.", "k": "padaum", "cover": "/books/content/67307/OEBPS/7570305756532313350_new-cover.jpg"}, {"id": "77027", "title": "A brief summary in plain language of the most important laws concerning women", "a": "Bodichon, Barbara Leigh Smith", "k": "barbaraleighsmithbodichon", "cover": "/books/content/77027/OEBPS/8595527619306737557_cover.jpg"}, {"id": "45767", "title": "Abraham Lincoln geschetst in zijn leven en daden", "a": "Bacon, G. W.", "k": "gwbacon", "cover": "/books/content/45767/OEBPS/653998824252094488_cover.jpg"}, {"id": "13910", "title": "A Book of Exposition", "a": "Nugent, Homer Heath", "k": "homerheathnugent", "cover": "/books/content/13910/OEBPS/4971137699460378026_13910-cover.png"}, {"id": "49273", "title": "ABC of the steel square and its uses", "a": "Hodgson, Fred T.", "k": "fredthodgson", "cover": "/books/content/49273/OEBPS/6115157580660785762_cover.jpg"}, {"id": "30243", "title": "ABC of Fox Hunting", "a": "Paul, Sir John Dean", "k": "sirjohndeanpaul", "cover": "/books/content/30243/OEBPS/522173951348962140_fox-cover2.jpg"}, {"id": "11708", "title": "Abraham Lincoln, a History — Volume 02", "a": "Nicolay, John G.", "k": "johngnicolay", "cover": "/books/content/11708/OEBPS/2525718838663867432_11708-cover.png"}, {"id": "6812", "title": "Abraham Lincoln: a History — Volume 01", "a": "Nicolay, John G.", "k": "johngnicolay", "cover": "/books/content/6812/OEBPS/2855526665963549840_6812-cover.png"}, {"id": "9237", "title": "A Bell's Biography", "a": "Hawthorne, Nathaniel", "k": "nathanielhawthorne", "cover": "/books/content/9237/OEBPS/1965062950568149296_9237-cover.png"}, {"id": "9250", "title": "A Book of Autographs", "a": "Hawthorne, Nathaniel", "k": "nathanielhawthorne", "cover": "/books/content/9250/OEBPS/3408573448646358957_9250-cover.png"}, {"id": "71991", "title": "A boy's text book on gas engines", "a": "Faurote, Fay Leone", "k": "fayleonefaurote", "cover": "/books/content/71991/OEBPS/9097557298458741858_cover.jpg"}, {"id": "22534", "title": "A Biographical Sketch of the Life and Character of Joseph Charless / In a Series of Letters to his Grandchildren", "a": "Charless, Charlotte Taylor Blow", "k": "charlottetaylorblowcharless", "cover": "/books/content/22534/OEBPS/5093577406555889910_22534-cover.png"}, {"id": "45005", "title": "Absurdities of immaterialism", "a": "Pratt, Orson", "k": "orsonpratt", "cover": "/books/content/45005/OEBPS/2562799495482422468_45005-cover.png"}, {"id": "40577", "title": "A Berzsenyi-leányok tizenkét vőlegénye: Tollrajzok a mai Budapestről", "a": "Ambrus, Zoltán", "k": "zoltanambrus", "cover": "/books/content/40577/OEBPS/4208051452980974641_40577-cover.png"}, {"id": "14200", "title": "Abbe Mouret's Transgression", "a": "Zola, Émile", "k": "emilezola", "cover": "/books/content/14200/OEBPS/6832524723134723419_14200-cover.png"}, {"id": "50973", "title": "\"About My Father's Business\": Work Amidst the Sick, the Sad, and the Sorrowing", "a": "Archer, Thomas", "k": "thomasarcher", "cover": "/books/content/50973/OEBPS/2270639215033360652_cover.jpg"}, {"id": "27919", "title": "Abissinia: Giornale di un viaggio", "a": "Vigoni, Giuseppe", "k": "giuseppevigoni", "cover": "/books/content/27919/OEBPS/4129835855083335709_27919-cover.png"}, {"id": "30883", "title": "Abessinien, das Alpenland unter den Tropen und seine Grenzländer", "a": "Andree, Richard", "k": "richardandree", "cover": "/books/content/30883/OEBPS/4590119406281225817_30883-cover.png"}, {"id": "69960", "title": "Abendfalter", "a": "Busse-Palma, Georg", "k": "georgbussepalma", "cover": "/books/content/69960/OEBPS/2077266572856927528_cover.jpg"}, {"id": "22145", "title": "A Book of Burlesques", "a": "Mencken, H. L.", "k": "hlmencken", "cover": "/books/content/22145/OEBPS/9162716709987756108_22145-cover.png"}, {"id": "19355", "title": "A Book of Prefaces", "a": "Mencken, H. L.", "k": "hlmencken", "cover": "/books/content/19355/OEBPS/4060993200493497285_19355-cover.png"}, {"id": "19968", "title": "A Busy Year at the Old Squire's", "a": "Stephens, C. A.", "k": "castephens", "cover": "/books/content/19968/OEBPS/9031540632840678713_19968-cover.png"}, {"id": "29915", "title": "About sugar buying for jobbers / How you can lessen business risks by trading in refined sugar futures", "a": "Dyer, B. W.", "k": "bwdyer", "cover": "/books/content/29915/OEBPS/7048939899644924881_29915-cover.png"}, {"id": "40291", "title": "Absalons Brønd", "a": "Bauditz, Sophus", "k": "sophusbauditz", "cover": "/books/content/40291/OEBPS/6928956156914369094_cover.jpg"}, {"id": "40589", "title": "A Brief History of Wood-engraving From Its Invention", "a": "Cundall, Joseph", "k": "josephcundall", "cover": "/books/content/40589/OEBPS/43110247987790609_40589-cover.png"}, {"id": "36703", "title": "A Bayard From Bengal / Being some account of the Magnificent and Spanking Career of Chunder Bindabun Bhosh,...", "a": "Anstey, F.", "k": "fanstey", "cover": "/books/content/36703/OEBPS/5761379414251566766_i_covert.jpg"}, {"id": "33538", "title": "A Bed of Roses", "a": "George, Walter Lionel", "k": "walterlionelgeorge", "cover": "/books/content/33538/OEBPS/9211778829741868676_33538-cover.png"}, {"id": "49238", "title": "A brief narrative of the Fourth Tennessee Cavalry Regiment, Wheeler's Corps, Army of Tennessee", "a": "Guild, George B.", "k": "georgebguild", "cover": "/books/content/49238/OEBPS/2923776933409052734_cover.jpg"}, {"id": "70398", "title": "A bibliography of the writings of D. H. Lawrence", "a": "McDonald, Edward D.", "k": "edwarddmcdonald", "cover": "/books/content/70398/OEBPS/6791239618338135785_cover.jpg"}, {"id": "14999", "title": "A Briefe Introduction to Geography", "a": "Pemble, William", "k": "williampemble", "cover": "/books/content/14999/OEBPS/8818623668746636618_14999-cover.png"}, {"id": "40161", "title": "A Book About Doctors", "a": "Jeaffreson, John Cordy", "k": "johncordyjeaffreson", "cover": "/books/content/40161/OEBPS/4276308081974360801_cover.jpg"}, {"id": "27785", "title": "A Book About Lawyers", "a": "Jeaffreson, John Cordy", "k": "johncordyjeaffreson", "cover": "/books/content/27785/OEBPS/2556893047810124778_27785-cover.png"}, {"id": "30153", "title": "Abuse, Torture, and Trauma and their Consequences and Effects", "a": "Vaknin, Samuel", "k": "samuelvaknin", "cover": "/books/content/30153/OEBPS/8432874871030975492_30153-cover.png"}, {"id": "46937", "title": "A Book of Cornwall", "a": "Baring-Gould, S.", "k": "sbaringgould", "cover": "/books/content/46937/OEBPS/1503315136446215495_cover.jpg"}, {"id": "51134", "title": "A Book of Dartmoor / Second Edition", "a": "Baring-Gould, S.", "k": "sbaringgould", "cover": "/books/content/51134/OEBPS/9214485708807650760_cover.jpg"}, {"id": "36638", "title": "A Book of Ghosts", "a": "Baring-Gould, S.", "k": "sbaringgould", "cover": "/books/content/36638/OEBPS/8350320038094445938_36638-cover.png"}, {"id": "51765", "title": "A Book of North Wales", "a": "Baring-Gould, S.", "k": "sbaringgould", "cover": "/books/content/51765/OEBPS/2656721755592074038_cover.jpg"}, {"id": "53945", "title": "A Book of the Cevennes", "a": "Baring-Gould, S.", "k": "sbaringgould", "cover": "/books/content/53945/OEBPS/2006566106099304189_cover.jpg"}, {"id": "52061", "title": "A Book of the Pyrenees", "a": "Baring-Gould, S.", "k": "sbaringgould", "cover": "/books/content/52061/OEBPS/1776565157733299015_cover.jpg"}, {"id": "51860", "title": "A Book of the Riviera", "a": "Baring-Gould, S.", "k": "sbaringgould", "cover": "/books/content/51860/OEBPS/1962484952849636699_cover.jpg"}, {"id": "48439", "title": "A book of the west. Volume 1, Devon", "a": "Baring-Gould, S.", "k": "sbaringgould", "cover": "/books/content/48439/OEBPS/4845600440417251532_coverpage.jpg"}, {"id": "73614", "title": "A book of the west. Volume 2, Cornwall", "a": "Baring-Gould, S.", "k": "sbaringgould", "cover": "/books/content/73614/OEBPS/1962814906692683175_cover.jpg"}, {"id": "34513", "title": "A Biographical Dictionary of Freethinkers of All Ages and Nations", "a": "Wheeler, J. M.", "k": "jmwheeler", "cover": "/books/content/34513/OEBPS/7543842284344570132_34513-cover.png"}, {"id": "71392", "title": "A bunch of rope yarns", "a": "King, Stanton H.", "k": "stantonhking", "cover": "/books/content/71392/OEBPS/1702660282733122721_cover.jpg"}, {"id": "19652", "title": "A Ball Player's Career / Being the Personal Experiences and Reminiscensces of Adrian C. Anson", "a": "Anson, Adrian C.", "k": "adriancanson", "cover": "/books/content/19652/OEBPS/2065930459071409699_19652-cover.png"}, {"id": "250", "title": "A Brief History of the Internet / The Bright Side: The Dark Side", "a": "Hart, Michael", "k": "michaelhart", "cover": "/books/content/250/OEBPS/452885265255172999_250-cover.png"}, {"id": "19578", "title": "A Ballad of John Silver", "a": "Masefield, John", "k": "johnmasefield", "cover": ""}, {"id": "63585", "title": "A bazini zsidók: Regény", "a": "Biró, Lajos", "k": "lajosbiro", "cover": "/books/content/63585/OEBPS/2447181778597720599_63585-cover.png"}, {"id": "3391", "title": "A Belated Guest (from Literary Friends and Acquaintance)", "a": "Howells, William Dean", "k": "williamdeanhowells", "cover": "/books/content/3391/OEBPS/9111419080687774356_3391-cover.png"}, {"id": "28727", "title": "A Boy's Town", "a": "Howells, William Dean", "k": "williamdeanhowells", "cover": "/books/content/28727/OEBPS/8483508389334489291_cover.jpg"}, {"id": "45030", "title": "A.B.C. of Snap Shooting: Sporting, Exhibition, and Military", "a": "Fletcher, Horace", "k": "horacefletcher", "cover": "/books/content/45030/OEBPS/2472216782466186865_cover.jpg"}, {"id": "58907", "title": "A B C of Gothic Architecture", "a": "Parker, John Henry", "k": "johnhenryparker", "cover": "/books/content/58907/OEBPS/7907133974567958452_cover.jpg"}, {"id": "50451", "title": "A Boy's Workshop: With plans and designs for in-door and out-door work", "a": "Craigin, Harry", "k": "harrycraigin", "cover": "/books/content/50451/OEBPS/2753122942095587057_i_cover.jpg"}, {"id": "43723", "title": "A Burlesque Translation of Homer", "a": "Bridges, active 1759-1775 Thomas", "k": "active17591775thomasbridges", "cover": "/books/content/43723/OEBPS/3024919926798099763_homer_title_002.jpg"}, {"id": "63925", "title": "A Blockaded Family: Life in Southern Alabama during the Civil War", "a": "Hague, Parthenia Antoinette", "k": "partheniaantoinettehague", "cover": "/books/content/63925/OEBPS/4227482931933455087_cover.jpg"}, {"id": "60904", "title": "A Book", "a": "Barnes, Djuna", "k": "djunabarnes", "cover": "/books/content/60904/OEBPS/5809367066313776055_cover.jpg"}, {"id": "18966", "title": "Abdallah eli nelilehtinen apila: Arabialainen kertomus", "a": "Laboulaye, Édouard", "k": "edouardlaboulaye", "cover": "/books/content/18966/OEBPS/2725829895316539371_18966-cover.png"}, {"id": "12184", "title": "Abroad with the Jimmies", "a": "Bell, Lilian", "k": "lilianbell", "cover": "/books/content/12184/OEBPS/865520572503107446_jimmies-cover.gif.png"}, {"id": "19961", "title": "Aboriginal Remains in Verde Valley, Arizona / Thirteenth Annual Report of the Bureau of Ethnology to the Secretary of the Smithsonian Institution, 1891-92, Government Printing Office, Washington, 1896, pages 179-262", "a": "Mindeleff, Cosmos", "k": "cosmosmindeleff", "cover": "/books/content/19961/OEBPS/7178399761983506126_19961-cover.png"}, {"id": "33904", "title": "A briefe discription of New England and the severall townes therein / together with the present government thereof", "a": "Maverick, Samuel", "k": "samuelmaverick", "cover": "/books/content/33904/OEBPS/3657052551868911886_33904-cover.png"}, {"id": "12911", "title": "A Backward Glance at Eighty: Recollections & Comment", "a": "Murdock, Charles A.", "k": "charlesamurdock", "cover": "/books/content/12911/OEBPS/5015340695699609857_12911-cover.png"}, {"id": "45673", "title": "A brief Journal of what passed in the City of Marseilles, while it was afflicted with the Plague, in the Year 1720", "a": "de Croislainte, Pichatty", "k": "pichattydecroislainte", "cover": "/books/content/45673/OEBPS/4928236061720276336_cover.jpg"}, {"id": "45024", "title": "A Boy Trooper with Sheridan", "a": "Allen, Stanton P.", "k": "stantonpallen", "cover": "/books/content/45024/OEBPS/6162223794204138365_cover.jpg"}, {"id": "26639", "title": "A Brief Commentary on the Apocalypse", "a": "Bliss, Sylvester", "k": "sylvesterbliss", "cover": "/books/content/26639/OEBPS/8632667504791153265_26639-cover.png"}, {"id": "20321", "title": "A Brief Account of the Destruction of the Indies / Or, a faithful NARRATIVE OF THE Horrid and Unexampled Massacres, Butcheries, and all manner of Cruelties, that Hell and Malice could invent, committed by the Popish Spanish Party on the inhabitants of West-India, TOGETHER With the Devastations of several Kingdoms in America by Fire and Sword, for the space of Forty and Two Years, from the time of its first Discovery by them.", "a": "Casas, Bartolomé de las", "k": "bartolomedelascasas", "cover": "/books/content/20321/OEBPS/3578849981335889551_20321-cover.png"}, {"id": "16251", "title": "A Book for Kids", "a": "Dennis, C. J.", "k": "cjdennis", "cover": "/books/content/16251/OEBPS/8669528087205778290_16251-cover.png"}, {"id": "52412", "title": "Abraham Lincoln and the Abolition of Slavery in the United States", "a": "Leland, Charles Godfrey", "k": "charlesgodfreyleland", "cover": "/books/content/52412/OEBPS/3867971983555337209_cover.jpg"}, {"id": "76434", "title": "A brief history of the Tenth Michigan Cavalry", "a": "Trowbridge, L. S.", "k": "lstrowbridge", "cover": "/books/content/76434/OEBPS/3228792146845975680_cover.jpg"}, {"id": "55216", "title": "A Brief History of Upshur County", "a": "Baird, G. H.", "k": "ghbaird", "cover": "/books/content/55216/OEBPS/8299965614792317434_cover.jpg"}, {"id": "44948", "title": "Abstracts of Papers Read at the First International Eugenics Congress / University of London, July, 1912", "a": "Congress, International Eugenics", "k": "internationaleugenicscongress", "cover": "/books/content/44948/OEBPS/5856337796443954338_cover.jpg"}, {"id": "33516", "title": "Abandoned", "a": "Verne, Jules", "k": "julesverne", "cover": "/books/content/33516/OEBPS/5761388350275568009_33516-cover.png"}, {"id": "13265", "title": "A Book of Fruits and Flowers", "a": "Anonymous", "k": "anonymous", "cover": "/books/content/13265/OEBPS/421734369272540685_title.png"}, {"id": "43883", "title": "A Brief History of the U. S. S. Imperator, One of the Two Largest Ships in the U. S. Navy.", "a": "Anonymous", "k": "anonymous", "cover": "/books/content/43883/OEBPS/707540887534081617_cover.jpg"}, {"id": "74664", "title": "A brief history of the 3rd Battalion, 1st Punjab Regiment", "a": "Anonymous", "k": "anonymous", "cover": "/books/content/74664/OEBPS/5844721533794067995_cover.jpg"}, {"id": "70464", "title": "Absolutely no paradox", "a": "Del Rey, Lester", "k": "lesterdelrey", "cover": "/books/content/70464/OEBPS/1047501271707183714_cover.jpg"}, {"id": "34135", "title": "A Book-Lover's Holidays in the Open", "a": "Roosevelt, Theodore", "k": "theodoreroosevelt", "cover": "/books/content/34135/OEBPS/5601174347557955087_34135-cover.png"}, {"id": "2836", "title": "Abraham Lincoln and the Union: A Chronicle of the Embattled North", "a": "Stephenson, Nathaniel W.", "k": "nathanielwstephenson", "cover": "/books/content/2836/OEBPS/555030542747987378_2836-cover.png"}, {"id": "48229", "title": "A Blue Devil of France: Epic figures and stories of the Great War, 1914-1918", "a": "Capart, G.-P.", "k": "gpcapart", "cover": "/books/content/48229/OEBPS/916048866145973721_cover.jpg"}, {"id": "52718", "title": "Abaellino der große Bandit", "a": "Zschokke, Heinrich", "k": "heinrichzschokke", "cover": "/books/content/52718/OEBPS/7038224868499698397_cover-page.jpg"}, {"id": "48851", "title": "A Balloon Ascension at Midnight", "a": "Hall, George Eli", "k": "georgeelihall", "cover": "/books/content/48851/OEBPS/8204709153981375895_cover.jpg"}, {"id": "64482", "title": "Abenteuer und Fahrten des Huckleberry Finn", "a": "Twain, Mark", "k": "marktwain", "cover": "/books/content/64482/OEBPS/4145910361587223868_cover.jpg"}, {"id": "30328", "title": "A Book of Cheerful Cats and Other Animated Animals", "a": "Francis, J. G.", "k": "jgfrancis", "cover": "/books/content/30328/OEBPS/2758744590563882153_30328-cover.png"}, {"id": "37703", "title": "About The Holy Bible: A Lecture", "a": "Ingersoll, Robert Green", "k": "robertgreeningersoll", "cover": "/books/content/37703/OEBPS/526947074617678651_37703-cover.png"}, {"id": "22608", "title": "A Book for All Readers / An Aid to the Collection, Use, and Preservation of Books and the Formation of Public and Private Libraries", "a": "Spofford, Ainsworth Rand", "k": "ainsworthrandspofford", "cover": "/books/content/22608/OEBPS/8128847844822937799_22608-cover.png"}, {"id": "70770", "title": "Abu-Seif", "a": "May, Karl", "k": "karlmay", "cover": "/books/content/70770/OEBPS/8686880189144430024_70770-cover.png"}, {"id": "19377", "title": "A Brief Account of the Rise and Progress of the People Called Quakers", "a": "Penn, William", "k": "williampenn", "cover": "/books/content/19377/OEBPS/3338676255239132278_19377-cover.png"}, {"id": "64626", "title": "Abury, A Temple of the British Druids, With Some Others, Described", "a": "Stukeley, William", "k": "williamstukeley", "cover": "/books/content/64626/OEBPS/7260704183469203109_cover.jpg"}, {"id": "34622", "title": "A Bibliotheca Nacional de Lisboa / Suas deficiencias e remedios d'essas deficiencias", "a": "da Cunha, Xavier", "k": "xavierdacunha", "cover": "/books/content/34622/OEBPS/1031141146847597208_34622-cover.png"}, {"id": "75560", "title": "A-B-C of housekeeping", "a": "Herrick, Christine Terhune", "k": "christineterhuneherrick", "cover": "/books/content/75560/OEBPS/3445952903674777712_cover.jpg"}, {"id": "21640", "title": "A Bid for Fortune; Or, Dr. Nikola's Vendetta", "a": "Boothby, Guy", "k": "guyboothby", "cover": "/books/content/21640/OEBPS/4205760966409433475_21640-cover.png"}, {"id": "23255", "title": "A British Islander / From \"Mackinac And Lake Stories\", 1899", "a": "Catherwood, Mary Hartwell", "k": "maryhartwellcatherwood", "cover": "/books/content/23255/OEBPS/5964638012172728619_23255-cover.png"}, {"id": "30117", "title": "ABC: Petits Contes", "a": "Lemaître, Jules", "k": "juleslemaitre", "cover": "/books/content/30117/OEBPS/5781894059545676728_cover.jpg"}, {"id": "23622", "title": "About Peggy Saville", "a": "Vaizey, Mrs. George de Horne", "k": "mrsgeorgedehornevaizey", "cover": "/books/content/23622/OEBPS/4199368025496576243_23622-cover.png"}, {"id": "29106", "title": "A Bride of the Plains", "a": "Orczy, Baroness Emmuska Orczy", "k": "baronessemmuskaorczyorczy", "cover": "/books/content/29106/OEBPS/5592876455753837738_29106-cover.png"}, {"id": "72209", "title": "A biographical memoir of the late Dr. Walter Oudney, Captain Hugh Clapperton, both of the Royal Navy, and Major Alex. Gordon Laing, all of whom died amid their active and enterprising endeavours to explore the interior of Africa", "a": "Nelson, Thomas", "k": "thomasnelson", "cover": "/books/content/72209/OEBPS/2746016676164431889_cover.jpg"}, {"id": "47379", "title": "A Bold Stroke for a Husband: A Comedy in Five Acts", "a": "Cowley, Hannah", "k": "hannahcowley", "cover": "/books/content/47379/OEBPS/3061693041757449951_47379-cover.png"}, {"id": "35434", "title": "Above the Snow Line: Mountaineering Sketches Between 1870 and 1880", "a": "Dent, C. T.", "k": "ctdent", "cover": "/books/content/35434/OEBPS/5950475042660090409_cover.jpg"}, {"id": "42085", "title": "A Bachelor Husband", "a": "Ayres, Ruby M.", "k": "rubymayres", "cover": "/books/content/42085/OEBPS/3256464488038561265_42085-cover.png"}, {"id": "34101", "title": "A Bilateral Division of the Parietal Bone in a Chimpanzee; with a Special Reference to the Oblique Sutures in the Parietal", "a": "Hrdlička, Aleš", "k": "aleshrdlicka", "cover": "/books/content/34101/OEBPS/465445214729026630_34101-cover.png"}, {"id": "45449", "title": "Abraham Lincoln: The Practical Mystic", "a": "Grierson, Francis", "k": "francisgrierson", "cover": "/books/content/45449/OEBPS/4121921169481768947_cover.jpg"}, {"id": "69199", "title": "A boke made by John Fryth, prysoner in the Tower of London / answerynge unto M. Mores letter, which he wrote agaynst the fyrste lytle treatyse that John Fryth made, concernynge the sacramente of the body and bloude of Christ", "a": "Frith, John", "k": "johnfrith", "cover": "/books/content/69199/OEBPS/2347818665611247443_cover.jpg"}, {"id": "52956", "title": "A Bitter Heritage: A Modern Story of Love and Adventure", "a": "Bloundelle-Burton, John", "k": "johnbloundelleburton", "cover": "/books/content/52956/OEBPS/3913459113532756608_52956-cover.png"}, {"id": "26056", "title": "A booke called the Foundacion of Rhetorike / because all other partes of Rhetorike are grounded thereupon, euery parte sette forthe in an Oracion vpon questions, verie profitable to bee knowen and redde", "a": "Rainolde, Richard", "k": "richardrainolde", "cover": "/books/content/26056/OEBPS/8377903810005187630_title.png"}, {"id": "52686", "title": "A Book of Birds", "a": "Moore-Park, Carton", "k": "cartonmoorepark", "cover": "/books/content/52686/OEBPS/1397575416900558657_cover.jpg"}, {"id": "63512", "title": "A' bölcseség vigasztalásai", "a": "Boethius", "k": "boethius", "cover": "/books/content/63512/OEBPS/4105394125753702925_63512-cover.png"}, {"id": "23803", "title": "A Border Ruffian / 1891", "a": "Janvier, Thomas A.", "k": "thomasajanvier", "cover": "/books/content/23803/OEBPS/7452493218702219204_23803-cover.png"}, {"id": "65476", "title": "A Bounty Boy / Being Some Adventures of a Christian Barbarian on an Unpremeditated Trip Round the World", "a": "Bullen, Frank Thomas", "k": "frankthomasbullen", "cover": "/books/content/65476/OEBPS/2770112989851332751_cover.jpg"}, {"id": "18573", "title": "Abraham Lincoln: An Horatian Ode", "a": "Stoddard, Richard Henry", "k": "richardhenrystoddard", "cover": "/books/content/18573/OEBPS/5410472067518211253_18573-cover.png"}, {"id": "46068", "title": "Abbotsford", "a": "Crockett, W. S.", "k": "wscrockett", "cover": "/books/content/46068/OEBPS/2146293268719260181_cover.jpg"}, {"id": "42289", "title": "Abbotsford", "a": "Crockett, W. S.", "k": "wscrockett", "cover": "/books/content/42289/OEBPS/4335004123536924330_img-cover.jpg"}, {"id": "53924", "title": "Abroad and at Home; Practical Hints for Tourists", "a": "Phillips, Morris", "k": "morrisphillips", "cover": "/books/content/53924/OEBPS/2121872516932753711_cover.jpg"}, {"id": "55097", "title": "A Book of Nimble Beasts: Bunny Rabbit, Squirrel, Toad, and \"Those Sort of People\"", "a": "English, Douglas", "k": "douglasenglish", "cover": "/books/content/55097/OEBPS/3142886841460941425_cover.jpg"}, {"id": "74514", "title": "Abroad with Mark Twain and Eugene Field", "a": "Fischer, Henry W.", "k": "henrywfischer", "cover": "/books/content/74514/OEBPS/1908305534422855123_cover.jpg"}, {"id": "72747", "title": "A British army, as it was,--is,--and ought to be", "a": "Campbell, James", "k": "jamescampbell", "cover": "/books/content/72747/OEBPS/7701819471947459190_cover.jpg"}, {"id": "57613", "title": "A Barren Title: A Novel", "a": "Speight, T. W.", "k": "twspeight", "cover": "/books/content/57613/OEBPS/667587228372547985_57613-cover.png"}, {"id": "4247", "title": "A Briefe and True Report of the New Found Land of Virginia", "a": "Harriot, Thomas", "k": "thomasharriot", "cover": "/books/content/4247/OEBPS/2851205794580536250_4247-cover.png"}, {"id": "16224", "title": "A Bibliographical, Antiquarian and Picturesque Tour in France and Germany, Volume One", "a": "Dibdin, Thomas Frognall", "k": "thomasfrognalldibdin", "cover": "/books/content/16224/OEBPS/8784825134594909995_16224-cover.png"}, {"id": "17624", "title": "A Bibliographical, Antiquarian and Picturesque Tour in France and Germany, Volume Three", "a": "Dibdin, Thomas Frognall", "k": "thomasfrognalldibdin", "cover": "/books/content/17624/OEBPS/7140547843739450119_17624-cover.png"}, {"id": "17107", "title": "A Bibliographical, Antiquarian and Picturesque Tour in France and Germany, Volume Two", "a": "Dibdin, Thomas Frognall", "k": "thomasfrognalldibdin", "cover": "/books/content/17107/OEBPS/1725428518112523014_17107-cover.png"}, {"id": "65055", "title": "A báróné ténsasszony: Regény", "a": "Tolnai, Lajos", "k": "lajostolnai", "cover": "/books/content/65055/OEBPS/858710482561701716_cover.jpg"}, {"id": "74057", "title": "A book of bridges", "a": "Sparrow, Walter Shaw", "k": "waltershawsparrow", "cover": "/books/content/74057/OEBPS/2468671719325889031_cover.jpg"}, {"id": "446", "title": "A Book of Remarkable Criminals", "a": "Irving, H. B.", "k": "hbirving", "cover": "/books/content/446/OEBPS/9048812745111354325_446-cover.png"}, {"id": "36790", "title": "A Book About the Theater", "a": "Matthews, Brander", "k": "brandermatthews", "cover": "/books/content/36790/OEBPS/1538414462128298090_36790-cover.png"}, {"id": "39152", "title": "A Biographical Sketch of some of the Most Eminent Individuals which the Principality of Wales has produced since the Reformation", "a": "Williams, Robert", "k": "robertwilliams", "cover": "/books/content/39152/OEBPS/3007192352988257387_39152-cover.png"}, {"id": "52706", "title": "About Paris", "a": "Davis, Richard Harding", "k": "richardhardingdavis", "cover": "/books/content/52706/OEBPS/7765158409165697551_cover.jpg"}, {"id": "61651", "title": "A Beginner's History of Philosophy, Vol. 1: Ancient and Mediæval Philosophy", "a": "Cushman, Herbert Ernest", "k": "herberternestcushman", "cover": "/books/content/61651/OEBPS/2793385799516205812_coverpage.jpg"}, {"id": "62663", "title": "A Beginner's History of Philosophy, Vol. 2: Modern Philosophy", "a": "Cushman, Herbert Ernest", "k": "herberternestcushman", "cover": "/books/content/62663/OEBPS/1041793781881356749_coverpage.jpg"}, {"id": "62995", "title": "A Book About Myself", "a": "Dreiser, Theodore", "k": "theodoredreiser", "cover": "/books/content/62995/OEBPS/1255998009977641429_cover.jpg"}, {"id": "65188", "title": "A Book of Medical Discourses, in Two Parts", "a": "Crumpler, Rebecca Lee", "k": "rebeccaleecrumpler", "cover": "/books/content/65188/OEBPS/3671993412081006293_cover.jpg"}, {"id": "27902", "title": "A Bird-Lover in the West", "a": "Miller, Olive Thorne", "k": "olivethornemiller", "cover": "/books/content/27902/OEBPS/3693329017747395107_27902-cover.png"}, {"id": "7806", "title": "A Boy's Ride", "a": "Zollinger, Gulielma", "k": "gulielmazollinger", "cover": "/books/content/7806/OEBPS/799961749129432916_7806-cover.png"}, {"id": "50349", "title": "A Basket of Barley Loaves", "a": "Miller, Mary Christina", "k": "marychristinamiller", "cover": "/books/content/50349/OEBPS/2656491537771687251_cover.jpg"}, {"id": "56297", "title": "A Boy of Old Japan", "a": "Van Bergen, R.", "k": "rvanbergen", "cover": "/books/content/56297/OEBPS/819428163033714506_cover.jpg"}, {"id": "38483", "title": "Abraham Lincoln: The True Story of a Great Life, Volume 1 (of 2)", "a": "Herndon, William Henry", "k": "williamhenryherndon", "cover": "/books/content/38483/OEBPS/5549773874774856847_38483-cover.png"}, {"id": "38484", "title": "Abraham Lincoln: The True Story of a Great Life, Volume 2 (of 2)", "a": "Herndon, William Henry", "k": "williamhenryherndon", "cover": "/books/content/38484/OEBPS/2631136981249865755_38484-cover.png"}, {"id": "55200", "title": "A Book About Words", "a": "Graham, G. F.", "k": "gfgraham", "cover": "/books/content/55200/OEBPS/8434145762516041504_cover.jpg"}, {"id": "24568", "title": "Aboriginal American Weaving", "a": "Kissell, Mary Lois", "k": "maryloiskissell", "cover": "/books/content/24568/OEBPS/4438463505864445689_24568-cover.png"}, {"id": "37072", "title": "A Brief Handbook of English Authors", "a": "Adams, Oscar Fay", "k": "oscarfayadams", "cover": "/books/content/37072/OEBPS/8148016752646694987_titlepage.jpg"}, {"id": "69062", "title": "A bacteriological study of ham souring", "a": "McBryde, Charles Neil", "k": "charlesneilmcbryde", "cover": "/books/content/69062/OEBPS/347918779719985725_i_cover.jpg"}, {"id": "64688", "title": "A barátfalvi lévita; Ujabb elbeszélések", "a": "Jókai, Mór", "k": "morjokai", "cover": "/books/content/64688/OEBPS/2273157326156087689_cover.jpg"}, {"id": "51258", "title": "A Bad Day for Vermin", "a": "Laumer, Keith", "k": "keithlaumer", "cover": "/books/content/51258/OEBPS/8771494570626920348_cover.jpg"}, {"id": "48763", "title": "A Book of Giants: Tales of Very Tall Men of Myth, Legend, History, and Science.", "a": "Lanier, Henry Wysham", "k": "henrywyshamlanier", "cover": "/books/content/48763/OEBPS/3304408512942688613_cover.jpg"}, {"id": "16461", "title": "A Bird's-Eye View of the Bible / Second Edition", "a": "Palmer, Frank Nelson", "k": "franknelsonpalmer", "cover": "/books/content/16461/OEBPS/6155986427729418276_16461-cover.png"}, {"id": "6489", "title": "A Book of Golden Deeds", "a": "Yonge, Charlotte M.", "k": "charlottemyonge", "cover": "/books/content/6489/OEBPS/5073197005370516198_6489-cover.png"}, {"id": "4267", "title": "Abbeychurch; Or, Self-Control and Self-Conceit", "a": "Yonge, Charlotte M.", "k": "charlottemyonge", "cover": "/books/content/4267/OEBPS/3635293766604317129_4267-cover.png"}, {"id": "56404", "title": "A Book of Gems, or, Choice selections from the writings of Benjamin Franklin", "a": "Franklin, Benjamin", "k": "benjaminfranklin", "cover": "/books/content/56404/OEBPS/90179423169707168_cover.jpg"}, {"id": "69198", "title": "A bird of passage", "a": "Croker, B. M.", "k": "bmcroker", "cover": "/books/content/69198/OEBPS/6336394513925403827_cover.jpg"}, {"id": "66603", "title": "A babonák könyve", "a": "Varga, János", "k": "janosvarga", "cover": "/books/content/66603/OEBPS/5403461527640528501_66603-cover.png"}, {"id": "22693", "title": "A Book of Myths", "a": "Lang, Jean", "k": "jeanlang", "cover": "/books/content/22693/OEBPS/2422692915117123649_22693-cover.png"}, {"id": "45397", "title": "A Boy Crusoe; or, The Golden Treasure of the Virgin Islands", "a": "Eric, Allan", "k": "allaneric", "cover": "/books/content/45397/OEBPS/5139516820351255099_img-cover.jpg"}, {"id": "31624", "title": "A Brief History of Element Discovery, Synthesis, and Analysis", "a": "Watson, Glen W.", "k": "glenwwatson", "cover": "/books/content/31624/OEBPS/7572714101545558995_bcover.png"}, {"id": "35965", "title": "Abroad at Home: American Ramblings, Observations, and Adventures of Julian Street", "a": "Street, Julian", "k": "julianstreet", "cover": "/books/content/35965/OEBPS/734914453087384561_35965-cover.png"}, {"id": "23107", "title": "A Book of Discovery / The History of the World's Exploration, From the Earliest Times to the Finding of the South Pole", "a": "Synge, M. B.", "k": "mbsynge", "cover": "/books/content/23107/OEBPS/1938870685672499784_23107-cover.png"}, {"id": "20083", "title": "A Boswell of Baghdad; With Diversions", "a": "Lucas, E. V.", "k": "evlucas", "cover": "/books/content/20083/OEBPS/1851583589220753768_20083-cover.png"}, {"id": "77608", "title": "A brand new world", "a": "Cummings, Ray", "k": "raycummings", "cover": "/books/content/77608/OEBPS/1106696598717647169_cover.jpg"}, {"id": "66254", "title": "A Briefe Discovrse of a Disease called the Suffocation of the Mother", "a": "Jorden, Edward", "k": "edwardjorden", "cover": "/books/content/66254/OEBPS/2634582537828886534_cover.jpg"}, {"id": "73335", "title": "Aberdeenshire", "a": "Mackie, Alexander", "k": "alexandermackie", "cover": "/books/content/73335/OEBPS/3523954190447856797_cover.jpg"}, {"id": "23170", "title": "A Brace Of Boys / 1867, From \"Little Brother\"", "a": "Ludlow, Fitz Hugh", "k": "fitzhughludlow", "cover": "/books/content/23170/OEBPS/243843172344106963_23170-cover.png"}, {"id": "67261", "title": "Aberglauben, Sitten und Gebräuche des sächsischen Obererzgebirges: Ein Beitrag zur Kenntnis des Volksglaubens und Volkslebens im Königreich Sachsen", "a": "Spiess, Moritz", "k": "moritzspiess", "cover": "/books/content/67261/OEBPS/9101675632770815816_cover.jpg"}, {"id": "2915", "title": "A Bit O' Love", "a": "Galsworthy, John", "k": "johngalsworthy", "cover": "/books/content/2915/OEBPS/1057000862807189824_2915-cover.png"}, {"id": "75431", "title": "Abracadabra & other satires", "a": "Galsworthy, John", "k": "johngalsworthy", "cover": "/books/content/75431/OEBPS/7583306614341852129_cover.jpg"}, {"id": "67944", "title": "A boy's-eye view of the Arctic", "a": "Rawson, Kennett Longley", "k": "kennettlongleyrawson", "cover": "/books/content/67944/OEBPS/8067131774129540408_cover.jpg"}, {"id": "54394", "title": "A Biography of the Signers of the Declaration of Independence, and of Washington and Patrick Henry / With an appendix, containing the Constitution of the United States, and other documents", "a": "Judson, L. Carroll", "k": "lcarrolljudson", "cover": "/books/content/54394/OEBPS/6729941221416635873_cover.jpg"}, {"id": "48874", "title": "A Brief History of Forestry. / In Europe, the United States and Other Countries", "a": "Fernow, B. E.", "k": "befernow", "cover": "/books/content/48874/OEBPS/7852321652262861584_cover.jpg"}, {"id": "75516", "title": "A book of dear dead women", "a": "Underwood, Edna Worthley", "k": "ednaworthleyunderwood", "cover": "/books/content/75516/OEBPS/2037570359097328328_cover.jpg"}, {"id": "52310", "title": "A Beacon for the Blind: Being a Life of Henry Fawcett, the Blind Postmaster-General", "a": "Holt, Winifred", "k": "winifredholt", "cover": "/books/content/52310/OEBPS/7080665088276687781_cover.jpg"}, {"id": "9950", "title": "Abhandlungen über die Fabel", "a": "Lessing, Gotthold Ephraim", "k": "gottholdephraimlessing", "cover": "/books/content/9950/OEBPS/2760354605858734753_9950-cover.png"}, {"id": "66391", "title": "A Book of Marionettes", "a": "Joseph, Helen Haiman", "k": "helenhaimanjoseph", "cover": "/books/content/66391/OEBPS/2101411529440447131_cover.jpg"}, {"id": "61207", "title": "A Book for the Hammock", "a": "Russell, William Clark", "k": "williamclarkrussell", "cover": "/books/content/61207/OEBPS/2873538152847235131_cover.jpg"}, {"id": "77738", "title": "A brief bibliography of books in English, Spanish and Portuguese, relating to the republics commonly called Latin American, with comments", "a": "Goldsmith, Peter H.", "k": "peterhgoldsmith", "cover": "/books/content/77738/OEBPS/6148134939155552658_cover.jpg"}, {"id": "24345", "title": "A Boy's Voyage Round the World", "a": "Smiles, Samuel", "k": "samuelsmiles", "cover": "/books/content/24345/OEBPS/351849370474855448_24345-cover.png"}, {"id": "37287", "title": "Abraham Lincoln's Religion", "a": "Peters, Madison Clinton", "k": "madisonclintonpeters", "cover": "/books/content/37287/OEBPS/3922832949532101356_37287-cover.png"}, {"id": "73972", "title": "A bankrupt heart, Vol. 1 (of 3)", "a": "Marryat, Florence", "k": "florencemarryat", "cover": "/books/content/73972/OEBPS/4540401897438294685_cover.jpg"}, {"id": "73973", "title": "A bankrupt heart, Vol. 2 (of 3)", "a": "Marryat, Florence", "k": "florencemarryat", "cover": "/books/content/73973/OEBPS/6705734265949697118_cover.jpg"}, {"id": "73974", "title": "A bankrupt heart, Vol. 3 (of 3)", "a": "Marryat, Florence", "k": "florencemarryat", "cover": "/books/content/73974/OEBPS/5760200280510077920_cover.jpg"}, {"id": "76780", "title": "A broken blossom, vol. 2 of 3", "a": "Marryat, Florence", "k": "florencemarryat", "cover": "/books/content/76780/OEBPS/773755807582566601_cover.jpg"}, {"id": "76781", "title": "A broken blossom, vol. 3 of 3", "a": "Marryat, Florence", "k": "florencemarryat", "cover": "/books/content/76781/OEBPS/7670058351556901654_cover.jpg"}, {"id": "56603", "title": "A boy in the Peninsular War", "a": "Blakeney, Robert", "k": "robertblakeney", "cover": "/books/content/56603/OEBPS/4648946944796115977_cover.jpg"}, {"id": "30004", "title": "A Bottle of Old Wine", "a": "Lewis, Richard O.", "k": "richardolewis", "cover": "/books/content/30004/OEBPS/8854978328206584546_30004-cover.png"}, {"id": "18543", "title": "Abrégé de l'Histoire universelle depuis Charlemagne jusques à Charlequint (Tome 1)", "a": "Voltaire", "k": "voltaire", "cover": "/books/content/18543/OEBPS/3052500057571876774_18543-cover.png"}, {"id": "51442", "title": "A Beginner's Psychology", "a": "Titchener, Edward Bradford", "k": "edwardbradfordtitchener", "cover": "/books/content/51442/OEBPS/7308160293861798268_cover.jpg"}, {"id": "11728", "title": "Abraham Lincoln: The People's Leader in the Struggle for National Existence", "a": "Putnam, George Haven", "k": "georgehavenputnam", "cover": "/books/content/11728/OEBPS/3925048160237177375_11728-cover.png"}, {"id": "49931", "title": "A Bullet for Cinderella", "a": "MacDonald, John D.", "k": "johndmacdonald", "cover": "/books/content/49931/OEBPS/8307850033690494674_cover.jpg"}, {"id": "6937", "title": "A Biography of Edmund Spenser", "a": "Hales, John W.", "k": "johnwhales", "cover": "/books/content/6937/OEBPS/6824270623227624721_6937-cover.png"}, {"id": "52057", "title": "Abandonment; or, Absolute Surrender to Divine Providence", "a": "de Caussade, Jean Pierre", "k": "jeanpierredecaussade", "cover": "/books/content/52057/OEBPS/3378930880008699068_cover.jpg"}, {"id": "2880", "title": "A Blot in the 'Scutcheon", "a": "Browning, Robert", "k": "robertbrowning", "cover": "/books/content/2880/OEBPS/7061748205495619715_2880-cover.png"}, {"id": "59133", "title": "A Body of Divinity, Vol. 1 (of 4) / Wherein the doctrines of the Christian religion are explained and defended, being the substance of several lectures on the Assembly's Larger Catechism", "a": "Ridgley, Thomas", "k": "thomasridgley", "cover": "/books/content/59133/OEBPS/8995475511463340043_cover.jpg"}, {"id": "62149", "title": "A Body of Divinity, Vol. 2 (of 4) / Wherein the doctrines of the Christian religion are explained and defended, being the substance of several lectures on the Assembly's Larger Catechism", "a": "Ridgley, Thomas", "k": "thomasridgley", "cover": "/books/content/62149/OEBPS/6616290246315175320_cover.jpg"}, {"id": "64185", "title": "A Body of Divinity, Vol. 3 (of 4) / Wherein the doctrines of the Christian religion are explained and defended, being the substance of several lectures on the Assembly's Larger Catechism", "a": "Ridgley, Thomas", "k": "thomasridgley", "cover": "/books/content/64185/OEBPS/2423574624400638071_cover.jpg"}, {"id": "65484", "title": "A Body of Divinity, Vol. 4 (of 4) / Wherein the doctrines of the Christian religion are explained and defended, being the substance of several lectures on the Assembly's Larger Catechism", "a": "Ridgley, Thomas", "k": "thomasridgley", "cover": "/books/content/65484/OEBPS/5732701736827465208_cover.jpg"}, {"id": "30385", "title": "A Burial Cave in Baja California / The Palmer Collection, 1887", "a": "Massey, William C.", "k": "williamcmassey", "cover": "/books/content/30385/OEBPS/6882280960748699684_30385-cover.png"}, {"id": "35004", "title": "Abbé Aubain and Mosaics", "a": "Mérimée, Prosper", "k": "prospermerimee", "cover": "/books/content/35004/OEBPS/2893955610981203289_35004-cover.png"}, {"id": "53775", "title": "A Bible School Manual: Studies in the Book of Revelation / An introduction, analysis, and notes, containing a concise interpretation according to the symbolic view, numerous references to authorities, and general mention of other interpretations, with the text of the American revised version edited in paragraphs, for the use of Bible students", "a": "Hunter, Stephen Alexander", "k": "stephenalexanderhunter", "cover": "/books/content/53775/OEBPS/7318412840806492082_cover.jpg"}, {"id": "72218", "title": "Abraham Poppius", "a": "Poppius, Abraham", "k": "abrahampoppius", "cover": "/books/content/72218/OEBPS/4650037976114425632_72218-cover.png"}, {"id": "3021", "title": "A Boy's Will", "a": "Frost, Robert", "k": "robertfrost", "cover": "/books/content/3021/OEBPS/3722778755184456486_3021-cover.png"}, {"id": "69702", "title": "A backwoods princess", "a": "Footner, Hulbert", "k": "hulbertfootner", "cover": "/books/content/69702/OEBPS/4971312721230661108_cover.jpg"}, {"id": "17315", "title": "Abe Lincoln Gets His Chance", "a": "Cavanah, Frances", "k": "francescavanah", "cover": "/books/content/17315/OEBPS/2856773066381578713_17315-cover.png"}, {"id": "62703", "title": "A Bill of Divorcement: A Play in Three Acts", "a": "Dane, Clemence", "k": "clemencedane", "cover": "/books/content/62703/OEBPS/8253017889243659992_cover.jpg"}, {"id": "71758", "title": "A brief and remarkable narrative of the life and extreme sufferings of Barnabas Downs, Jun.", "a": "Downs, Barnabas", "k": "barnabasdowns", "cover": "/books/content/71758/OEBPS/1994706152704395006_cover.jpg"}, {"id": "50548", "title": "A beginner's history", "a": "Mace, William H.", "k": "williamhmace", "cover": "/books/content/50548/OEBPS/2568738501626403564_cover.jpg"}, {"id": "11521", "title": "A Beleaguered City / Being a Narrative of Certain Recent Events in the City of Semur, in the Department of the Haute Bourgogne. A Story of the Seen and the Unseen", "a": "Oliphant, Mrs.", "k": "mrsoliphant", "cover": "/books/content/11521/OEBPS/8282579428453014730_11521-cover.png"}, {"id": "19250", "title": "‘Abdu'l-Bahá in London", "a": "ʻAbdu'l-Bahá", "k": "ʻabdulbaha", "cover": "/books/content/19250/OEBPS/6080051983140487418_19250-cover.png"}, {"id": "19292", "title": "‘Abdu'l-Bahá's Tablet to Dr. Forel", "a": "ʻAbdu'l-Bahá", "k": "ʻabdulbaha", "cover": "/books/content/19292/OEBPS/2070864010219731057_19292-cover.png"}, {"id": "45754", "title": "ABC Butter Making: A Hand-Book for the Beginner", "a": "Burch, Frederick S.", "k": "fredericksburch", "cover": "/books/content/45754/OEBPS/56909416212707179_cover.jpg"}, {"id": "9", "title": "Abraham Lincoln's First Inaugural Address", "a": "Lincoln, Abraham", "k": "abrahamlincoln", "cover": "/books/content/9/OEBPS/2721537627217896997_cover.jpg"}, {"id": "61966", "title": "Abraham Lincoln's Lost Speech, May 29, 1856 / A Souvenir of the Eleventh Annual Lincoln Dinner of the Republican Club of the City of New York, at the Waldorf, February 12, 1897", "a": "Lincoln, Abraham", "k": "abrahamlincoln", "cover": "/books/content/61966/OEBPS/1025337150599766353_cover.jpg"}, {"id": "8", "title": "Abraham Lincoln's Second Inaugural Address", "a": "Lincoln, Abraham", "k": "abrahamlincoln", "cover": "/books/content/8/OEBPS/2612157095215558555_cover.jpg"}, {"id": "18379", "title": "Abraham Lincoln", "a": "Charnwood, Baron Godfrey Rathbone Benson", "k": "barongodfreyrathbonebensoncharnwood", "cover": "/books/content/18379/OEBPS/2792389866336664186_18379-cover.png"}, {"id": "77690", "title": "A bold bad butterfly", "a": "Herford, Oliver", "k": "oliverherford", "cover": "/books/content/77690/OEBPS/7500899405955884140_cover.jpg"}, {"id": "32307", "title": "A Brief Account of Radio-activity", "a": "Venable, F. P.", "k": "fpvenable", "cover": "/books/content/32307/OEBPS/8455783926143234672_32307-cover.png"}, {"id": "43533", "title": "A Brief Bible History: A Survey of the Old and New Testaments", "a": "Boyd, James Oscar", "k": "jamesoscarboyd", "cover": "/books/content/43533/OEBPS/2433026928453394016_coverpage.jpg"}, {"id": "29245", "title": "A Breath of Prairie and other stories", "a": "Lillibridge, Will", "k": "willlillibridge", "cover": "/books/content/29245/OEBPS/8366669516352461524_29245-cover.png"}, {"id": "33410", "title": "A-Birding on a Bronco", "a": "Bailey, Florence Merriam", "k": "florencemerriambailey", "cover": "/books/content/33410/OEBPS/4203817534776986337_cover.jpg"}, {"id": "41189", "title": "A Book o' Nine Tales.", "a": "Bates, Arlo", "k": "arlobates", "cover": "/books/content/41189/OEBPS/1791344424298907761_front_cover.jpg"}, {"id": "69033", "title": "A Bakony (1. kötet)", "a": "Eötvös, Károly", "k": "karolyeotvos", "cover": "/books/content/69033/OEBPS/8808345333088256548_cover.jpg"}, {"id": "69034", "title": "A Bakony (2. kötet)", "a": "Eötvös, Károly", "k": "karolyeotvos", "cover": "/books/content/69034/OEBPS/4842985522712595871_cover.jpg"}, {"id": "65797", "title": "A balatoni utazás vége", "a": "Eötvös, Károly", "k": "karolyeotvos", "cover": "/books/content/65797/OEBPS/782402318185786411_cover.jpg"}, {"id": "75144", "title": "A boys' life of Booker T. Washington", "a": "Jackson, Walter Clinton", "k": "walterclintonjackson", "cover": "/books/content/75144/OEBPS/5433135131699050708_cover.jpg"}, {"id": "1632", "title": "A Book of Scoundrels", "a": "Whibley, Charles", "k": "charleswhibley", "cover": "/books/content/1632/OEBPS/7736025888053796082_1632-cover.png"}, {"id": "59332", "title": "Abaft the Funnel", "a": "Kipling, Rudyard", "k": "rudyardkipling", "cover": "/books/content/59332/OEBPS/1304214795123147814_cover.jpg"}, {"id": "62099", "title": "A bűvös erszény és egyéb elbeszélések", "a": "Krúdy, Gyula", "k": "gyulakrudy", "cover": "/books/content/62099/OEBPS/6547158787497244289_62099-cover.png"}, {"id": "13109", "title": "About Ireland", "a": "Linton, E. Lynn", "k": "elynnlinton", "cover": "/books/content/13109/OEBPS/778304071872121358_13109-cover.png"}, {"id": "38388", "title": "A Bride from the Bush", "a": "Hornung, E. W.", "k": "ewhornung", "cover": "/books/content/38388/OEBPS/1322417187990716392_cover.jpg"}, {"id": "47811", "title": "\"Abe\" Lincoln's Anecdotes and Stories / A Collection of the Best Stories Told by Lincoln Which Made Him Famous as America's Best Story Teller", "a": "Unknown", "k": "unknown", "cover": "/books/content/47811/OEBPS/3203240642813242671_cover.jpg"}, {"id": "62383", "title": "A Biblia Sagrada, Contendo o Velho e o Novo Testamento", "a": "Unknown", "k": "unknown", "cover": "/books/content/62383/OEBPS/3367312854957879290_cover.jpg"}, {"id": "59290", "title": "A Biography of Henry Clay, the Senator from Kentucky / Containing Also, a Complete Report of All His Speeches; Selections From His Private Correspondence; Eulogies in the Senate and House; and a Poem, by George D. Prentice, Esq.", "a": "Unknown", "k": "unknown", "cover": "/books/content/59290/OEBPS/2515931309841398868_cover.jpg"}, {"id": "24692", "title": "A Bit of Sunshine", "a": "Unknown", "k": "unknown", "cover": "/books/content/24692/OEBPS/819626971723270654_24692-cover.png"}, {"id": "36009", "title": "A Book Written by the Spirits of the So-Called Dead", "a": "Unknown", "k": "unknown", "cover": "/books/content/36009/OEBPS/4649686191777286710_cover.jpg"}, {"id": "43482", "title": "A Book of Bryn Mawr Stories", "a": "Unknown", "k": "unknown", "cover": "/books/content/43482/OEBPS/5169991404820434413_i01.jpg"}, {"id": "56467", "title": "A Book of Distinctive Interiors", "a": "Unknown", "k": "unknown", "cover": "/books/content/56467/OEBPS/5624765987216831903_cover.jpg"}, {"id": "33190", "title": "A Book of Epigrams", "a": "Unknown", "k": "unknown", "cover": "/books/content/33190/OEBPS/9105204910813504506_33190-cover.png"}, {"id": "8565", "title": "A Book of German Lyrics", "a": "Unknown", "k": "unknown", "cover": "/books/content/8565/OEBPS/428323054328209341_8565-cover.png"}, {"id": "37845", "title": "A Book of Irish Verse / Selected from modern writers, with an introduction and notes by W. B. Yeats", "a": "Unknown", "k": "unknown", "cover": "/books/content/37845/OEBPS/6164283308347435355_37845-cover.png"}, {"id": "57218", "title": "A Book of Jewish Thoughts", "a": "Unknown", "k": "unknown", "cover": "/books/content/57218/OEBPS/2590037374867540068_cover.jpg"}, {"id": "18274", "title": "A Book of Natural History / Young Folks' Library Volume XIV.", "a": "Unknown", "k": "unknown", "cover": "/books/content/18274/OEBPS/3897470625544253683_cover-t.jpg"}, {"id": "7535", "title": "A Book of Old Ballads — Complete", "a": "Unknown", "k": "unknown", "cover": "/books/content/7535/OEBPS/4248413642547695621_7535-cover.png"}, {"id": "7531", "title": "A Book of Old Ballads — Volume 1", "a": "Unknown", "k": "unknown", "cover": "/books/content/7531/OEBPS/5410698200216930322_7531-cover.png"}, {"id": "7532", "title": "A Book of Old Ballads — Volume 2", "a": "Unknown", "k": "unknown", "cover": "/books/content/7532/OEBPS/4991640328474524639_7532-cover.png"}, {"id": "7533", "title": "A Book of Old Ballads — Volume 3", "a": "Unknown", "k": "unknown", "cover": "/books/content/7533/OEBPS/1913244736093686661_7533-cover.png"}, {"id": "7534", "title": "A Book of Old Ballads — Volume 4", "a": "Unknown", "k": "unknown", "cover": "/books/content/7534/OEBPS/1875125395404894252_7534-cover.png"}, {"id": "53951", "title": "A Book of Simples", "a": "Unknown", "k": "unknown", "cover": "/books/content/53951/OEBPS/9055640006596699171_cover.jpg"}, {"id": "58447", "title": "A Book of the United States / Exhibiting its geography, divisions, constitution, and government ... and presenting a view of the republic generally, and of the individual states; together with a condensed history of the land, from its first discovery to the present time. The biography of about two hundred of the leading men: a description of the principal cities and towns; with statistical tables", "a": "Unknown", "k": "unknown", "cover": "/books/content/58447/OEBPS/7158466201668169780_cover.jpg"}, {"id": "57761", "title": "A Brief History of the King's Royal Rifle Corps", "a": "Unknown", "k": "unknown", "cover": "/books/content/57761/OEBPS/2995459178363093428_cover.jpg"}, {"id": "28198", "title": "A Budget of Christmas Tales by Charles Dickens and Others", "a": "Unknown", "k": "unknown", "cover": "/books/content/28198/OEBPS/1292066055098905766_titlepage.jpg"}, {"id": "2831", "title": "A Bundle of Ballads", "a": "Unknown", "k": "unknown", "cover": "/books/content/2831/OEBPS/1877617121628160046_2831-cover.png"}, {"id": "70928", "title": "A book of Christmas verse", "a": "Unknown", "k": "unknown", "cover": "/books/content/70928/OEBPS/918643126600295977_cover.jpg"}, {"id": "68657", "title": "A book of images", "a": "Unknown", "k": "unknown", "cover": "/books/content/68657/OEBPS/2142595484378735788_cover.jpg"}, {"id": "74619", "title": "A book of women's verse", "a": "Unknown", "k": "unknown", "cover": "/books/content/74619/OEBPS/6530588885308058623_cover.jpg"}, {"id": "38056", "title": "Abraham Lincoln and the London Punch / Cartoons, Comments and Poems, Published in the London Charivari, During the American Civil War (1861-1865)", "a": "Unknown", "k": "unknown", "cover": "/books/content/38056/OEBPS/7390848261727296157_38056-cover.png"}, {"id": "23460", "title": "Abroad", "a": "Unknown", "k": "unknown", "cover": "/books/content/23460/OEBPS/2493095027029294170_fcover.jpg"}, {"id": "48468", "title": "A \"Bawl\" for American Cricket", "a": "Wister, Jones", "k": "joneswister", "cover": "/books/content/48468/OEBPS/2912572521500797969_cover.jpg"}, {"id": "62428", "title": "A Battle for Right; Or, A Clash of Wits", "a": "Carter, Nicholas", "k": "nicholascarter", "cover": "/books/content/62428/OEBPS/1306725519261711407_cover.jpg"}, {"id": "63143", "title": "A Broken Bond; Or, The Man Without Morals", "a": "Carter, Nicholas", "k": "nicholascarter", "cover": "/books/content/63143/OEBPS/7913104773566761373_cover.jpg"}, {"id": "18237", "title": "A Bird Calendar for Northern India", "a": "Dewar, Douglas", "k": "douglasdewar", "cover": "/books/content/18237/OEBPS/638735899618150532_18237-cover.png"}, {"id": "14027", "title": "Abydos / De Aarde en haar Volken, 1906", "a": "Amélineau, E.", "k": "eamelineau", "cover": "/books/content/14027/OEBPS/1435625398316484346_14027-cover.png"}, {"id": "54693", "title": "A Book for a Rainy Day; or, Recollections of the Events of the Years 1766-1833", "a": "Smith, John Thomas", "k": "johnthomassmith", "cover": "/books/content/54693/OEBPS/2292529782531910417_cover.jpg"}, {"id": "40499", "title": "Abridgment of the Debates of Congress, from 1789 to 1856, Vol. 1 (of 16)", "a": "Congress, United States.", "k": "unitedstatescongress", "cover": "/books/content/40499/OEBPS/3636860168181584240_title.jpg"}, {"id": "40851", "title": "Abridgment of the Debates of Congress, from 1789 to 1856, Vol. 2 (of 16)", "a": "Congress, United States.", "k": "unitedstatescongress", "cover": "/books/content/40851/OEBPS/5479931025523309551_titlepage.jpg"}, {"id": "54345", "title": "Abridgment of the Debates of Congress, from 1789 to 1856, Vol. 3 (of 16)", "a": "Congress, United States.", "k": "unitedstatescongress", "cover": "/books/content/54345/OEBPS/8839577664125285571_cover.jpg"}, {"id": "47289", "title": "Abridgment of the Debates of Congress, from 1789 to 1856, Vol. 4 (of 16)", "a": "Congress, United States.", "k": "unitedstatescongress", "cover": "/books/content/47289/OEBPS/7517105624793729258_cover.jpg"}, {"id": "13646", "title": "A Book of Nonsense", "a": "Lear, Edward", "k": "edwardlear", "cover": "/books/content/13646/OEBPS/8062723644104047648_13646-cover.png"}, {"id": "15151", "title": "A Book of the Play / Studies and Illustrations of Histrionic Story, Life, and Character", "a": "Cook, Dutton", "k": "duttoncook", "cover": "/books/content/15151/OEBPS/2020659485271673499_15151-cover.png"}, {"id": "76172", "title": "A bad penny", "a": "Wheelwright, John T.", "k": "johntwheelwright", "cover": "/books/content/76172/OEBPS/671697380667149191_cover.jpg"}, {"id": "27660", "title": "A Book Without a Title", "a": "Nathan, George Jean", "k": "georgejeannathan", "cover": "/books/content/27660/OEBPS/8432955172667251989_27660-cover.png"}, {"id": "11172", "title": "Abraham Lincoln: A Play", "a": "Drinkwater, John", "k": "johndrinkwater", "cover": "/books/content/11172/OEBPS/930521203880711812_11172-cover.png"}, {"id": "40517", "title": "A Bottle in the Smoke: A Tale of Anglo-Indian Life", "a": "Rae, Janet Milne", "k": "janetmilnerae", "cover": "/books/content/40517/OEBPS/4638991565242379655_cover.jpg"}, {"id": "54402", "title": "A Broken Journey / Wanderings from the Hoang-Ho to the Island of Saghalien and the Upper Reaches of the Amur River", "a": "Gaunt, Mary", "k": "marygaunt", "cover": "/books/content/54402/OEBPS/899084034057686177_cover.jpg"}, {"id": "76672", "title": "A brief narrative of the life of Mrs. Adele M. Jewel (being deaf and dumb)", "a": "Jewel, Adele M.", "k": "adelemjewel", "cover": "/books/content/76672/OEBPS/2355162659159347024_cover.jpg"}, {"id": "53307", "title": "A Birder's Guide to North Dakota", "a": "Zimmer, Kevin J.", "k": "kevinjzimmer", "cover": "/books/content/53307/OEBPS/744730384504382315_cover.jpg"}, {"id": "51997", "title": "A Book of Poems, Al Que Quiere!", "a": "Williams, William Carlos", "k": "williamcarloswilliams", "cover": "/books/content/51997/OEBPS/7751104856690670038_cover.jpg"}, {"id": "19605", "title": "A Book of Quaker Saints", "a": "Hodgkin, L. V.", "k": "lvhodgkin", "cover": "/books/content/19605/OEBPS/2106059796714098123_19605-cover.png"}, {"id": "68905", "title": "A brazileira de Prazins: scenas do Minho.", "a": "Branco, Camilo Castelo", "k": "camilocastelobranco", "cover": "/books/content/68905/OEBPS/3811319858324401267_prazins_cover.jpg"}, {"id": "39497", "title": "A Breeze from the Woods, 2nd Ed.", "a": "Bartlett, W. C.", "k": "wcbartlett", "cover": "/books/content/39497/OEBPS/5554626828112892743_cover.jpg"}, {"id": "75627", "title": "A borrowed sister", "a": "White, Eliza Orne", "k": "elizaornewhite", "cover": "/books/content/75627/OEBPS/6292478102097694798_cover.jpg"}, {"id": "24082", "title": "A Broader Mission for Liberal Education / Baccalaureate Address, Delivered in Agricultural College Chapel, Sunday June 9, 1901", "a": "Worst, John H.", "k": "johnhworst", "cover": "/books/content/24082/OEBPS/3015027503918559998_24082-cover.png"}, {"id": "40015", "title": "A Boy Scout's Courage", "a": "Griggs, Edward Howard", "k": "edwardhowardgriggs", "cover": "/books/content/40015/OEBPS/9194949637680355198_img-cover.jpg"}, {"id": "50200", "title": "A Brief Account of the Educational Publishing Business in the United States", "a": "Pulsifer, William Edmond", "k": "williamedmondpulsifer", "cover": "/books/content/50200/OEBPS/3746568054692754658_cover.jpg"}, {"id": "5052", "title": "Absalom's Hair", "a": "Bjørnson, Bjørnstjerne", "k": "bjørnstjernebjørnson", "cover": "/books/content/5052/OEBPS/954060842116537030_5052-cover.png"}, {"id": "51619", "title": "Absalomin tukka", "a": "Bjørnson, Bjørnstjerne", "k": "bjørnstjernebjørnson", "cover": "/books/content/51619/OEBPS/1258440361838498991_51619-cover.png"}, {"id": "27838", "title": "A Bachelor's Dream", "a": "Duchess", "k": "duchess", "cover": "/books/content/27838/OEBPS/1434675056348109787_27838-cover.png"}, {"id": "1953", "title": "A Book of Strife in the Form of The Diary of an Old Soul", "a": "MacDonald, George", "k": "georgemacdonald", "cover": "/books/content/1953/OEBPS/335817683370143390_1953-cover.png"}, {"id": "50919", "title": "A Bibliography of Bibliography; Or, a Handy Book About Books Which Relate to Books", "a": "Sabin, Joseph", "k": "josephsabin", "cover": "/books/content/50919/OEBPS/6349843349633614359_cover.jpg"}, {"id": "41014", "title": "Abolition a Sedition, by a Northern Man", "a": "Colton, Calvin", "k": "calvincolton", "cover": "/books/content/41014/OEBPS/2928676966392349351_cover.jpg"}, {"id": "31048", "title": "A Battery at Close Quarters / A Paper Read before the Ohio Commandery of the Loyal Legion, October 6, 1909", "a": "Neil, Henry M.", "k": "henrymneil", "cover": "/books/content/31048/OEBPS/1732881212260585931_cover.jpg"}, {"id": "50494", "title": "Abner Daniel: A Novel", "a": "Harben, Will N.", "k": "willnharben", "cover": "/books/content/50494/OEBPS/710302677181662315_cover.jpg"}, {"id": "76232", "title": "Abbey", "a": "Guernsey, Lucy Ellen", "k": "lucyellenguernsey", "cover": "/books/content/76232/OEBPS/8450343829569585561_image001.jpg"}, {"id": "15820", "title": "A Book for the Young", "a": "French, Sarah", "k": "sarahfrench", "cover": "/books/content/15820/OEBPS/1788194843137674233_15820-cover.png"}, {"id": "2425", "title": "A Bundle of Letters", "a": "James, Henry", "k": "henryjames", "cover": "/books/content/2425/OEBPS/9029317236736229876_2425-cover.png"}, {"id": "57635", "title": "A Brief Sketch of the Long and Varied Career of Marshall MacDermott, Esq., J.P. of Adelaide, South Australia", "a": "MacDermott, Marshall", "k": "marshallmacdermott", "cover": "/books/content/57635/OEBPS/7723038158485129038_cover.jpg"}, {"id": "34164", "title": "A Blot on the Scutcheon", "a": "Knowles, Mabel Winifred", "k": "mabelwinifredknowles", "cover": "/books/content/34164/OEBPS/8512878426288704170_34164-cover.png"}, {"id": "25989", "title": "A Beautiful Alien", "a": "Magruder, Julia", "k": "juliamagruder", "cover": "/books/content/25989/OEBPS/9010688708278257690_icover.jpg"}, {"id": "53816", "title": "A Book of Christian Sonnets", "a": "Allen, William", "k": "williamallen", "cover": "/books/content/53816/OEBPS/3209884389182822941_cover.jpg"}, {"id": "43113", "title": "A Blind Esperantist's Trip to Finland and Sweden, to Attend the Fourteenth International Esperanto Congress", "a": "Merrick, W. Percy", "k": "wpercymerrick", "cover": "/books/content/43113/OEBPS/8301003990026184666_cover.jpg"}, {"id": "12829", "title": "Abélard, Tome I", "a": "de Rémusat, Charles", "k": "charlesderemusat", "cover": "/books/content/12829/OEBPS/1397002795852338817_12829-cover.png"}, {"id": "13807", "title": "Abélard, Tome II", "a": "de Rémusat, Charles", "k": "charlesderemusat", "cover": "/books/content/13807/OEBPS/115059034199100382_13807-cover.png"}, {"id": "45946", "title": "A-B-C of Gardening", "a": "Rexford, Eben E.", "k": "ebenerexford", "cover": "/books/content/45946/OEBPS/6940142107225836910_cover.jpg"}, {"id": "46052", "title": "A-B-C of Vegetable Gardening", "a": "Rexford, Eben E.", "k": "ebenerexford", "cover": "/books/content/46052/OEBPS/2691390052771341275_cover.jpg"}, {"id": "56346", "title": "A Book of American Explorers", "a": "Higginson, Thomas Wentworth", "k": "thomaswentworthhigginson", "cover": "/books/content/56346/OEBPS/8893670400182173243_cover.jpg"}, {"id": "906", "title": "Abraham Lincoln", "a": "Lowell, James Russell", "k": "jamesrusselllowell", "cover": "/books/content/906/OEBPS/71586295936763105_906-cover.png"}, {"id": "54367", "title": "A Blundering Boy: A Humorous Story", "a": "Munro, Bruce Weston", "k": "brucewestonmunro", "cover": "/books/content/54367/OEBPS/4658177926500382722_cover.jpg"}, {"id": "54092", "title": "A Bundle of Letters from over the Sea", "a": "Robinson, Louise B.", "k": "louisebrobinson", "cover": "/books/content/54092/OEBPS/2937385101433025984_cover.jpg"}, {"id": "42526", "title": "Abraham Lincoln", "a": "Curtis, William Eleroy", "k": "williameleroycurtis", "cover": "/books/content/42526/OEBPS/6044977852042920967_cover.jpg"}, {"id": "32868", "title": "A Biblia da Humanidade", "a": "de Quental, Antero", "k": "anterodequental", "cover": "/books/content/32868/OEBPS/5059297478307140930_32868-cover.png"}, {"id": "55330", "title": "A Biography of Rev. Henry Ward Beecher", "a": "Beecher, William Constantine", "k": "williamconstantinebeecher", "cover": "/books/content/55330/OEBPS/4025427916485157226_cover.jpg"}, {"id": "43118", "title": "A Bevy of Girls", "a": "Meade, L. T.", "k": "ltmeade", "cover": "/books/content/43118/OEBPS/176526880590582909_43118-cover.png"}, {"id": "25467", "title": "A Big Temptation", "a": "Meade, L. T.", "k": "ltmeade", "cover": "/books/content/25467/OEBPS/5925501365533525190_cover.jpg"}, {"id": "28564", "title": "A Bunch of Cherries: A Story of Cherry Court School", "a": "Meade, L. T.", "k": "ltmeade", "cover": "/books/content/28564/OEBPS/808148590277729338_img-cover.jpg"}, {"id": "5724", "title": "A Book of Operas: Their Histories, Their Plots, and Their Music", "a": "Krehbiel, Henry Edward", "k": "henryedwardkrehbiel", "cover": "/books/content/5724/OEBPS/1837885966313171403_5724-cover.png"}, {"id": "20169", "title": "A bihari remete, és egyéb történetek", "a": "Kárpáti, Aurél", "k": "aurelkarpati", "cover": "/books/content/20169/OEBPS/3820515883629676506_20169-cover.png"}, {"id": "26356", "title": "A brother to dragons, and other old-time tales", "a": "Rives, Amélie", "k": "amelierives", "cover": "/books/content/26356/OEBPS/3722535793975952594_cover.jpg"}, {"id": "42089", "title": "Abolitionism Exposed! / Proving the the Principles of Abolitionism are Injurious to the Slaves Themselves, Destructive to This Nation, and Contrary to the Express Commands of God", "a": "Sleigh, W. W.", "k": "wwsleigh", "cover": "/books/content/42089/OEBPS/6588296280610211952_cover.jpg"}, {"id": "50744", "title": "A British Rifle Man / The Journals and Correspondence of Major George Simmons, Rifle Brigade, During the Peninsular War and the Campaign of Waterloo", "a": "Simmons, George", "k": "georgesimmons", "cover": "/books/content/50744/OEBPS/1819986278430191685_cover.jpg"}, {"id": "54833", "title": "Abraham Lincoln in Our Own County", "a": "Beardsley, Henry Mahan", "k": "henrymahanbeardsley", "cover": "/books/content/54833/OEBPS/5155407449738158041_cover.jpg"}, {"id": "72505", "title": "Abraham Lincoln", "a": "Wilson, Woodrow", "k": "woodrowwilson", "cover": "/books/content/72505/OEBPS/8639068363002552672_cover.jpg"}, {"id": "38206", "title": "A Boy of the Dominion: A Tale of Canadian Immigration", "a": "Brereton, F. S.", "k": "fsbrereton", "cover": "/books/content/38206/OEBPS/4955922499186313876_img-cover.jpg"}, {"id": "6896", "title": "A Brief History of the United States", "a": "McMaster, John Bach", "k": "johnbachmcmaster", "cover": "/books/content/6896/OEBPS/3349164331679791802_6896-cover.png"}, {"id": "6434", "title": "A Brief History of the United States", "a": "Steele, Joel Dorman", "k": "joeldormansteele", "cover": "/books/content/6434/OEBPS/4763145405330031322_6434-cover.png"}, {"id": "7948", "title": "Abbotsford and Newstead Abbey", "a": "Irving, Washington", "k": "washingtonirving", "cover": "/books/content/7948/OEBPS/7567958510160680499_7948-cover.png"}, {"id": "34915", "title": "Abolition Fanaticism in New York / Speech of a Runaway Slave from Baltimore, at an Abolition / Meeting in New York, Held May 11, 1847", "a": "Douglass, Frederick", "k": "frederickdouglass", "cover": "/books/content/34915/OEBPS/3665352155295275554_cover-s.jpg"}, {"id": "50079", "title": "A Book on Vegetable Dyes", "a": "Mairet, Ethel", "k": "ethelmairet", "cover": "/books/content/50079/OEBPS/5750805003555473596_title-page.jpg"}, {"id": "22558", "title": "Abrégé de l'Histoire Générale des Voyages (Tome 1)", "a": "La Harpe, Jean-François de", "k": "jeanfrancoisdelaharpe", "cover": "/books/content/22558/OEBPS/3115707969053368400_22558-cover.png"}, {"id": "24768", "title": "Abrégé de l'Histoire Générale des Voyages (Tome 2)", "a": "La Harpe, Jean-François de", "k": "jeanfrancoisdelaharpe", "cover": "/books/content/24768/OEBPS/3151682612915837416_24768-cover.png"}, {"id": "38256", "title": "Abrégé de l'Histoire Générale des Voyages (Tome 3)", "a": "La Harpe, Jean-François de", "k": "jeanfrancoisdelaharpe", "cover": "/books/content/38256/OEBPS/2813461932848377946_38256-cover.png"}, {"id": "38257", "title": "Abrégé de l'Histoire Générale des Voyages (Tome 4)", "a": "La Harpe, Jean-François de", "k": "jeanfrancoisdelaharpe", "cover": "/books/content/38257/OEBPS/1202710017251731529_38257-cover.png"}, {"id": "38258", "title": "Abrégé de l'Histoire Générale des Voyages (Tome 5)", "a": "La Harpe, Jean-François de", "k": "jeanfrancoisdelaharpe", "cover": "/books/content/38258/OEBPS/9098584129987580180_38258-cover.png"}, {"id": "42635", "title": "Abrégé de l'Histoire Générale des Voyages (Tome 6)", "a": "La Harpe, Jean-François de", "k": "jeanfrancoisdelaharpe", "cover": "/books/content/42635/OEBPS/93778232221368832_42635-cover.png"}, {"id": "60934", "title": "A Belle of the Fifties / Memoirs of Mrs. Clay of Alabama, covering social and political life in Washington and the South, 1853-1866. Put into narrative form by Ada Sterling", "a": "Clay-Clopton, Virginia", "k": "virginiaclayclopton", "cover": "/books/content/60934/OEBPS/973720541035067764_cover.jpg"}, {"id": "72194", "title": "Abrégé de l'histoire de l'Ukraine", "a": "Hrushevskyi, Mykhailo", "k": "mykhailohrushevskyi", "cover": "/books/content/72194/OEBPS/5441956087940931743_cover.jpg"}, {"id": "18714", "title": "Abe and Mawruss: Being Further Adventures of Potash and Perlmutter", "a": "Glass, Montague", "k": "montagueglass", "cover": "/books/content/18714/OEBPS/2077056394099181476_cover01pp.jpg"}, {"id": "36467", "title": "A Butterfly on the Wheel: A Novel", "a": "Thorne, Guy", "k": "guythorne", "cover": "/books/content/36467/OEBPS/5005630043043010163_cover.jpg"}, {"id": "60514", "title": "About Algeria: Algiers, Tlemçen, Constantine, Biskra, Timgad", "a": "Thomas-Stanford, Charles", "k": "charlesthomasstanford", "cover": "/books/content/60514/OEBPS/102901946053807874_cover.jpg"}, {"id": "23100", "title": "A Budget of Paradoxes, Volume I", "a": "De Morgan, Augustus", "k": "augustusdemorgan", "cover": "/books/content/23100/OEBPS/4318477903527106663_23100-cover.png"}, {"id": "26408", "title": "A Budget of Paradoxes, Volume II", "a": "De Morgan, Augustus", "k": "augustusdemorgan", "cover": "/books/content/26408/OEBPS/8452112438787416622_26408-cover.png"}, {"id": "18540", "title": "Abraham Lincoln", "a": "Eddy, T. M.", "k": "tmeddy", "cover": "/books/content/18540/OEBPS/8640472957848705351_18540-cover.png"}, {"id": "53884", "title": "A Biblical and Theological Dictionary / explanatory of the history, manners, and customs of the Jews, and neighbouring nations", "a": "Watson, Richard", "k": "richardwatson", "cover": "/books/content/53884/OEBPS/3923933709219579414_cover.jpg"}, {"id": "25238", "title": "A batalha de Toro", "a": "Barata, António Francisco", "k": "antoniofranciscobarata", "cover": "/books/content/25238/OEBPS/2384359300643297852_25238-cover.png"}, {"id": "32779", "title": "Above the Battle", "a": "Rolland, Romain", "k": "romainrolland", "cover": "/books/content/32779/OEBPS/1187767685061317634_32779-cover.png"}, {"id": "72035", "title": "A bord de la Junon", "a": "Lemay, Gaston", "k": "gastonlemay", "cover": "/books/content/72035/OEBPS/8371850276559363852_cover.jpg"}, {"id": "32773", "title": "About London", "a": "Ritchie, J. Ewing", "k": "jewingritchie", "cover": "/books/content/32773/OEBPS/1348185684714413195_32773-cover.png"}, {"id": "17155", "title": "About orchids", "a": "Boyle, Frederick", "k": "frederickboyle", "cover": "/books/content/17155/OEBPS/1760581970059404622_17155-cover.png"}, {"id": "44512", "title": "Abel Sánchez: Una Historia de Pasión", "a": "de Unamuno, Miguel", "k": "migueldeunamuno", "cover": "/books/content/44512/OEBPS/467577717054061946_cover.jpg"}, {"id": "65596", "title": "A Brief History of Printing in England / A Short History of Printing in England from Caxton to the Present Time", "a": "Hamilton, Frederick W.", "k": "frederickwhamilton", "cover": "/books/content/65596/OEBPS/8683091268206538783_cover.jpg"}, {"id": "65585", "title": "A Brief History of Printing. Part II: The Economic History of Printing", "a": "Hamilton, Frederick W.", "k": "frederickwhamilton", "cover": "/books/content/65585/OEBPS/1083551453032937117_cover.jpg"}, {"id": "33828", "title": "Abbreviations and Signs / A Primer of Information about Abbreviations and Signs, with Classified Lists of Those in Most Common Use", "a": "Hamilton, Frederick W.", "k": "frederickwhamilton", "cover": "/books/content/33828/OEBPS/2421979049787543853_33828-cover.png"}, {"id": "41605", "title": "Abigail Adams and Her Times", "a": "Richards, Laura Elizabeth Howe", "k": "lauraelizabethhowerichards", "cover": "/books/content/41605/OEBPS/7392247094291647168_cover.jpg"}, {"id": "75929", "title": "Abraham Lincoln raittiusmiehenä ja lyhyitä piirteitä hänen elämänkerrastaan", "a": "Ilmonen, S.", "k": "silmonen", "cover": "/books/content/75929/OEBPS/9199761117165390857_75929-cover.png"}, {"id": "71872", "title": "A book of martyrs", "a": "Comer, Cornelia A. P.", "k": "corneliaapcomer", "cover": "/books/content/71872/OEBPS/6105861423085988799_cover.jpg"}, {"id": "59728", "title": "Abbr.", "a": "Riley, Frank", "k": "frankriley", "cover": "/books/content/59728/OEBPS/4582437717704610869_cover.jpg"}, {"id": "25939", "title": "A Bibliography of the writings in Prose and Verse of George Henry Borrow", "a": "Wise, Thomas James", "k": "thomasjameswise", "cover": "/books/content/25939/OEBPS/5875804883881554551_25939-cover.png"}, {"id": "35106", "title": "Abington Abbey: A Novel", "a": "Marshall, Archibald", "k": "archibaldmarshall", "cover": "/books/content/35106/OEBPS/5601333454132497888_35106-cover.png"}, {"id": "11959", "title": "A Brief Memoir with Portions of the Diary, Letters, and Other Remains, / of Eliza Southall, Late of Birmingham, England", "a": "Southall, Eliza Allen", "k": "elizaallensouthall", "cover": "/books/content/11959/OEBPS/2845459932213582697_11959-cover.png"}, {"id": "30724", "title": "Absolution", "a": "Viebig, Clara", "k": "claraviebig", "cover": "/books/content/30724/OEBPS/6275573715808844391_30724-cover.png"}, {"id": "30435", "title": "A Book of Sibyls: Miss Barbauld, Miss Edgeworth, Mrs Opie, Miss Austen", "a": "Ritchie, Anne Thackeray", "k": "annethackerayritchie", "cover": "/books/content/30435/OEBPS/4662732671532830020_30435-cover.png"}, {"id": "3313", "title": "A Bit of Old China", "a": "Stoddard, Charles Warren", "k": "charleswarrenstoddard", "cover": "/books/content/3313/OEBPS/1336788053875585800_3313-cover.png"}, {"id": "63205", "title": "A Boy's Trip Across the Plains", "a": "Preston, Laura", "k": "laurapreston", "cover": "/books/content/63205/OEBPS/8300999024033068660_cover.jpg"}, {"id": "29020", "title": "A Boy I Knew and Four Dogs", "a": "Hutton, Laurence", "k": "laurencehutton", "cover": "/books/content/29020/OEBPS/4255233601214871696_cover.jpg"}, {"id": "64712", "title": "A brief guide to the Food Collection", "a": "Museum, Bethnal Green", "k": "bethnalgreenmuseum", "cover": "/books/content/64712/OEBPS/8184193541525668284_cover.jpg"}, {"id": "38374", "title": "Abraham Lincoln: Was He a Christian?", "a": "Remsburg, John E.", "k": "johneremsburg", "cover": "/books/content/38374/OEBPS/5557253316191512369_38374-cover.png"}, {"id": "10037", "title": "A Beautiful Possibility", "a": "Black, Edith Ferguson", "k": "edithfergusonblack", "cover": "/books/content/10037/OEBPS/4200276646343299765_10037-cover.png"}, {"id": "52917", "title": "A Bible History of Baptism", "a": "Baird, Samuel J.", "k": "samueljbaird", "cover": "/books/content/52917/OEBPS/3987632093421404768_cover.jpg"}, {"id": "76426", "title": "A blighted life", "a": "Lytton, Baroness Rosina Bulwer Lytton", "k": "baronessrosinabulwerlyttonlytton", "cover": "/books/content/76426/OEBPS/6743086798372077754_cover.jpg"}, {"id": "52017", "title": "A Boy's Fortune; Or, The Strange Adventures of Ben Baker", "a": "Alger, Jr. Horatio", "k": "jrhoratioalger", "cover": "/books/content/52017/OEBPS/7004390392727809659_cover.jpg"}, {"id": "52232", "title": "A Bible Hand-Book", "a": "Holliday, F. C.", "k": "fcholliday", "cover": "/books/content/52232/OEBPS/2402515692893264583_cover.jpg"}, {"id": "62770", "title": "A \"booklet of verse\"", "a": "Myers-Funnell, Rozelle V.", "k": "rozellevmyersfunnell", "cover": "/books/content/62770/OEBPS/6734645491532094376_cover.jpg"}, {"id": "34068", "title": "A brief sketch of the work of Matthew Fontaine Maury during the war, 1861-1865", "a": "Maury, Richard L.", "k": "richardlmaury", "cover": "/books/content/34068/OEBPS/2032088217767953826_34068-cover.png"}, {"id": "19811", "title": "A Book of English Prose / Part II, Arranged for Secondary and High Schools", "a": "Lubbock, Percy", "k": "percylubbock", "cover": "/books/content/19811/OEBPS/3975378566471475790_19811-cover.png"}, {"id": "28538", "title": "A Bookful of Girls", "a": "Fuller, Anna", "k": "annafuller", "cover": "/books/content/28538/OEBPS/2684570079197868477_28538-cover.png"}]}