{"key": "frederickwhymper", "name": "Whymper, Frederick", "books": [{"id": "39341", "title": "The Sea: Its Stirring Story of Adventure, Peril, & Heroism. Volume 1", "cover": "/books/content/39341/OEBPS/3954865444278375296_cover.jpg"}, {"id": "39342", "title": "The Sea: Its Stirring Story of Adventure, Peril, & Heroism. Volume 2", "cover": "/books/content/39342/OEBPS/4287655432772870041_39342-cover.png"}, {"id": "39343", "title": "The Sea: Its Stirring Story of Adventure, Peril, & Heroism. Volume 3", "cover": "/books/content/39343/OEBPS/1958784938473074465_39343-cover.png"}, {"id": "45033", "title": "The Sea: Its Stirring Story of Adventure, Peril, & Heroism. Volume 4", "cover": "/books/content/45033/OEBPS/5165026325331759922_cover.jpg"}]}