{"key": "richardsouth", "name": "South, Richard", "books": [{"id": "43713", "title": "The Butterflies of the British Isles", "cover": "/books/content/43713/OEBPS/4614102320351138894_cover.jpg"}, {"id": "41782", "title": "The Moths of the British Isles, First Series / Comprising the Families Sphingidæ to Noctuidæ", "cover": "/books/content/41782/OEBPS/869235675050605677_41782-cover.png"}, {"id": "41920", "title": "The Moths of the British Isles, Second Series / Comprising the Families Noctuidæ to Hepialidæ", "cover": "/books/content/41920/OEBPS/5425309437782539997_41920-cover.png"}]}