{"authorCount": 30, "authors": [{"key": "alicevanleercarrick", "name": "Carrick, Alice van Leer", "count": 1}, {"key": "alicevansittartstrettelcarr", "name": "Carr, Alice Vansittart Strettel", "count": 4}, {"key": "annieroecarr", "name": "Carr, Annie Roe", "count": 7}, {"key": "berthacarrharris", "name": "Carr-Harris, Bertha", "count": 1}, {"key": "charlesecarryl", "name": "Carryl, Charles E.", "count": 2}, {"key": "concepcionarenaldegarciacarrasco", "name": "Carrasco, Concepción Arenal de García", "count": 1}, {"key": "edithcarrington", "name": "Carrington, Edith", "count": 1}, {"key": "edonaldcarr", "name": "Carr, E. Donald", "count": 1}, {"key": "edwinhamlincarr", "name": "Carr, Edwin Hamlin", "count": 1}, {"key": "emiliocarrere", "name": "Carrere, Emilio", "count": 1}, {"key": "enriquegilycarrasco", "name": "Carrasco, Enrique Gil y", "count": 1}, {"key": "fitzroycarrington", "name": "Carrington, Fitz Roy", "count": 1}, {"key": "guywetmorecarryl", "name": "Carryl, Guy Wetmore", "count": 6}, {"key": "haydencarruth", "name": "Carruth, Hayden", "count": 2}, {"key": "henrybcarrington", "name": "Carrington, Henry B.", "count": 1}, {"key": "herbertwildoncarr", "name": "Carr, Herbert Wildon", "count": 1}, {"key": "herewardcarrington", "name": "Carrington, Hereward", "count": 5}, {"key": "jcomynscarr", "name": "Carr, J. Comyns", "count": 2}, {"key": "johndcarrick", "name": "Carrick, John D.", "count": 2}, {"key": "lewiscarroll", "name": "Carroll, Lewis", "count": 30}, {"key": "lymancarrier", "name": "Carrier, Lyman", "count": 1}, {"key": "mitchellcarroll", "name": "Carroll, Mitchell", "count": 1}, {"key": "robertscarroll", "name": "Carroll, Robert S.", "count": 1}, {"key": "sarahprattcarr", "name": "Carr, Sarah Pratt", "count": 3}, {"key": "sirjohncarr", "name": "Carr, Sir John", "count": 3}, {"key": "terrycarr", "name": "Carr, Terry", "count": 1}, {"key": "valentinocarrera", "name": "Carrera, Valentino", "count": 6}, {"key": "williamcarroll", "name": "Carroll, William", "count": 1}, {"key": "williamhcarr", "name": "Carr, William H.", "count": 1}, {"key": "zulmacarraud", "name": "Carraud, Zulma", "count": 2}]}