{"authorCount": 10, "authors": [{"key": "albertcoste", "name": "Coste, Albert", "count": 1}, {"key": "annamillercostantini", "name": "Costantini, Anna Miller", "count": 1}, {"key": "edwardcostello", "name": "Costello, Edward", "count": 1}, {"key": "enricocosta", "name": "Costa, Enrico", "count": 4}, {"key": "fernandescosta", "name": "Costa, Fernandes", "count": 2}, {"key": "jacostello", "name": "Costello, J. A.", "count": 1}, {"key": "josesoaresdacunhaecosta", "name": "Costa, José Soares da Cunha e", "count": 1}, {"key": "laurencecostelloe", "name": "Costelloe, Laurence", "count": 1}, {"key": "louisastuartcostello", "name": "Costello, Louisa Stuart", "count": 1}, {"key": "pfcostello", "name": "Costello, P. F.", "count": 1}]}