{"authorCount": 9, "authors": [{"key": "allertonscushman", "name": "Cushman, Allerton S.", "count": 1}, {"key": "calebcushing", "name": "Cushing, Caleb", "count": 1}, {"key": "charlesphelpscushing", "name": "Cushing, Charles Phelps", "count": 1}, {"key": "cushag", "name": "Cushag", "count": 1}, {"key": "frankhamiltoncushing", "name": "Cushing, Frank Hamilton", "count": 4}, {"key": "herberternestcushman", "name": "Cushman, Herbert Ernest", "count": 2}, {"key": "lutherstearnscushing", "name": "Cushing, Luther Stearns", "count": 1}, {"key": "maxpearsoncushing", "name": "Cushing, Max Pearson", "count": 1}, {"key": "robertcushman", "name": "Cushman, Robert", "count": 1}]}