{"authorCount": 17, "authors": [{"key": "charlesmauricedavies", "name": "Davies, Charles Maurice", "count": 1}, {"key": "ebenezerdavies", "name": "Davies, Ebenezer", "count": 1}, {"key": "emilydavies", "name": "Davies, Emily", "count": 1}, {"key": "etegladavies", "name": "Davies, E. Tegla", "count": 1}, {"key": "gchristopherdavies", "name": "Davies, G. Christopher", "count": 2}, {"key": "headmasterofcarnarvonschoolwilliamdavies", "name": "Davies, Head-master of Carnarvon School William", "count": 1}, {"key": "jonathanceredigdavies", "name": "Davies, Jonathan Ceredig", "count": 1}, {"key": "lintondavies", "name": "Davies, Linton", "count": 1}, {"key": "mariathompsondaviess", "name": "Daviess, Maria Thompson", "count": 12}, {"key": "marycarolyndavies", "name": "Davies, Mary Carolyn", "count": 1}, {"key": "randalldavies", "name": "Davies, Randall", "count": 4}, {"key": "rricedavies", "name": "Davies, R. Rice", "count": 1}, {"key": "sirjohndavies", "name": "Davies, Sir John", "count": 2}, {"key": "thomasdavies", "name": "Davies, Thomas", "count": 1}, {"key": "whdavies", "name": "Davies, W. H.", "count": 3}, {"key": "williamgabrieldavies", "name": "Davies, William Gabriel", "count": 1}, {"key": "williamwatkindavies", "name": "Davies, William Watkin", "count": 1}]}