{"authorCount": 8, "authors": [{"key": "arnodoschfleurot", "name": "Dosch-Fleurot, Arno", "count": 1}, {"key": "augustojoaquimalvesdossantos", "name": "dos Santos, Augusto Joaquim Alves", "count": 1}, {"key": "cafonsodossantos", "name": "dos Santos, C. Afonso", "count": 1}, {"key": "carlodossi", "name": "Dossi, Carlo", "count": 1}, {"key": "fyodordostoyevsky", "name": "Dostoyevsky, Fyodor", "count": 54}, {"key": "johndospassos", "name": "Dos Passos, John", "count": 7}, {"key": "johnrdospassos", "name": "Dos Passos, John R.", "count": 1}, {"key": "lfdostoevskaia", "name": "Dostoevskaia, L. F.", "count": 1}]}