{"authorCount": 7, "authors": [{"key": "alfredlichtenstein", "name": "Lichtenstein, Alfred", "count": 2}, {"key": "andrelichtenberger", "name": "Lichtenberger, André", "count": 2}, {"key": "furstvonkarlmaxlichnowsky", "name": "Lichnowsky, Fürst von Karl Max", "count": 1}, {"key": "henrilichtenberger", "name": "Lichtenberger, Henri", "count": 1}, {"key": "mechtildlichnowsky", "name": "Lichnowsky, Mechtild", "count": 1}, {"key": "sidneylicht", "name": "Licht, Sidney", "count": 1}, {"key": "theodorelicquet", "name": "Licquet, Théodore", "count": 1}]}