{"authorCount": 7, "authors": [{"key": "axellundegard", "name": "Lundegård, Axel", "count": 1}, {"key": "ernstlundquist", "name": "Lundquist, Ernst", "count": 1}, {"key": "hughlundsford", "name": "Lundsford, Hugh", "count": 1}, {"key": "isidorlundstrom", "name": "Lundström, Isidor", "count": 1}, {"key": "mariannelundegardhagberg", "name": "Lundegård-Hagberg, Marianne", "count": 1}, {"key": "matthewnathanaellundquist", "name": "Lundquist, Matthew Nathanael", "count": 1}, {"key": "rhlundie", "name": "Lundie, R. H.", "count": 1}]}