{"authorCount": 7, "authors": [{"key": "albertmoll", "name": "Moll, Albert", "count": 1}, {"key": "clarkrmollenhoff", "name": "Mollenhoff, Clark R.", "count": 1}, {"key": "dinamollingerhooyer", "name": "Mollinger-Hooyer, Dina", "count": 1}, {"key": "geraldmolloy", "name": "Molloy, Gerald", "count": 2}, {"key": "jfitzgeraldmolloy", "name": "Molloy, J. Fitzgerald", "count": 1}, {"key": "johnmollard", "name": "Mollard, John", "count": 1}, {"key": "johnwmollett", "name": "Mollett, John W.", "count": 1}]}