{"authorCount": 9, "authors": [{"key": "aldencharlesnoble", "name": "Noble, Alden Charles", "count": 1}, {"key": "alfrednoble", "name": "Noble, Alfred", "count": 1}, {"key": "antoniopereiranobre", "name": "Nobre, António Pereira", "count": 2}, {"key": "gilbertnobbs", "name": "Nobbs, Gilbert", "count": 1}, {"key": "henrygeorgestebbinsnoble", "name": "Noble, Henry George Stebbins", "count": 1}, {"key": "louislegrandnoble", "name": "Noble, Louis Legrand", "count": 1}, {"key": "mosesjamesnobbs", "name": "Nobbs, Moses James", "count": 1}, {"key": "riccardonobili", "name": "Nobili, Riccardo", "count": 1}, {"key": "tcnoble", "name": "Noble, T. C.", "count": 1}]}