{"authorCount": 15, "authors": [{"key": "albertofelicianomarquespereira", "name": "Pereira, Alberto Feliciano Marques", "count": 1}, {"key": "arthuraperera", "name": "Perera, Arthur A.", "count": 1}, {"key": "eduardocnpereira", "name": "Pereira, Eduardo C. N.", "count": 1}, {"key": "elekperegriny", "name": "Peregriny, Elek", "count": 1}, {"key": "felixalvespereira", "name": "Pereira, Félix Alves", "count": 1}, {"key": "gabrielpereira", "name": "Pereira, Gabriel", "count": 1}, {"key": "isaacloebperetz", "name": "Peretz, Isaac Loeb", "count": 2}, {"key": "jbperes", "name": "Pérès, J.-B.", "count": 1}, {"key": "jeanmperez", "name": "Pérez, Jean M.", "count": 1}, {"key": "josegestosoyperez", "name": "Pérez, José Gestoso y", "count": 1}, {"key": "josenebotperez", "name": "Pérez, José Nebot", "count": 2}, {"key": "josephinapintocarneiroperestrello", "name": "Perestrello, Josephina Pinto Carneiro", "count": 1}, {"key": "miguelagustinperez", "name": "Pérez, Miguel Agustin", "count": 1}, {"key": "modestoperez", "name": "Perez, Modesto", "count": 1}, {"key": "mthperelaer", "name": "Perelaer, M. T. H.", "count": 6}]}