{"authorCount": 8, "authors": [{"key": "arthurschnitzler", "name": "Schnitzler, Arthur", "count": 13}, {"key": "bsschneck", "name": "Schneck, B. S.", "count": 1}, {"key": "carlschneider", "name": "Schneider, Carl", "count": 1}, {"key": "charleshschnapps", "name": "Schnapps, Charles H.", "count": 1}, {"key": "eberhardschnetzler", "name": "Schnetzler, Eberhard", "count": 1}, {"key": "georgschneidemuhl", "name": "Schneidemühl, Georg", "count": 1}, {"key": "juliusschnauss", "name": "Schnauss, Julius", "count": 1}, {"key": "normanhschneider", "name": "Schneider, Norman H.", "count": 1}]}