{"authorCount": 8, "authors": [{"key": "charlesscudamore", "name": "Scudamore, Charles", "count": 1}, {"key": "horaceelishascudder", "name": "Scudder, Horace Elisha", "count": 6}, {"key": "jamesscurry", "name": "Scurry, James", "count": 1}, {"key": "johnscudder", "name": "Scudder, John", "count": 1}, {"key": "paulscudo", "name": "Scudo, Paul", "count": 2}, {"key": "samuelhubbardscudder", "name": "Scudder, Samuel Hubbard", "count": 1}, {"key": "vincentscully", "name": "Scully, Vincent", "count": 1}, {"key": "wcscully", "name": "Scully, W. C.", "count": 7}]}