{"authorCount": 12, "authors": [{"key": "blackieson", "name": "Son, Blackie &", "count": 5}, {"key": "crosbylockwoodandson", "name": "Son, Crosby Lockwood and", "count": 2}, {"key": "georgebellsons", "name": "Sons, George Bell &", "count": 2}, {"key": "isaacpitmansons", "name": "Sons, Isaac Pitman &", "count": 1}, {"key": "jhatchardandson", "name": "Son, J. Hatchard and", "count": 1}, {"key": "johnwmasuryson", "name": "Son, John W. Masury &", "count": 1}, {"key": "louissonolet", "name": "Sonolet, Louis", "count": 1}, {"key": "shangjiesong", "name": "Song, Shangjie", "count": 1}, {"key": "wehillsons", "name": "Sons, W.E. Hill &", "count": 1}, {"key": "williamblackwoodandsons", "name": "Sons, William Blackwood and", "count": 1}, {"key": "yesong", "name": "Song, Ye", "count": 1}, {"key": "yingxingsong", "name": "Song, Yingxing", "count": 1}]}