{"authorCount": 7, "authors": [{"key": "bertholdviertel", "name": "Viertel, Berthold", "count": 1}, {"key": "claraviebig", "name": "Viebig, Clara", "count": 8}, {"key": "edmevielliard", "name": "Vielliard, Edme", "count": 1}, {"key": "georgesylvesterviereck", "name": "Viereck, George Sylvester", "count": 2}, {"key": "hermanknickerbockerviele", "name": "Vielé, Herman Knickerbocker", "count": 1}, {"key": "joaoaugustonovaesvieira", "name": "Vieira, João Augusto Novaes", "count": 1}, {"key": "joseaugustovieira", "name": "Vieira, José Augusto", "count": 1}]}