{"authorCount": 234, "prefixes": [{"prefix": "wea", "count": 12}, {"prefix": "web", "count": 35}, {"prefix": "wec", "count": 1}, {"prefix": "wed", "count": 5}, {"prefix": "wee", "count": 11}, {"prefix": "weg", "count": 4}, {"prefix": "wei", "count": 29}, {"prefix": "wel", "count": 43}, {"prefix": "wem", "count": 1}, {"prefix": "wen", "count": 14}, {"prefix": "wer", "count": 14}, {"prefix": "wes", "count": 46}, {"prefix": "wet", "count": 10}, {"prefix": "weu", "count": 1}, {"prefix": "wev", "count": 1}, {"prefix": "wey", "count": 7}]}